[
  {
    "platform" : "IPHONE_ARM64",
    "searchTime" : "2023-07-27T03:26:51.979Z[UTC]",
    "searchQuery" : "p",
    "searchInteractionURIs" : [
    ]
  },
  {
    "platform" : "IPHONE",
    "searchTime" : "2023-07-27T03:27:04.488Z[UTC]",
    "searchQuery" : "post",
    "searchInteractionURIs" : [
      "spotify:artist:246dkjvS1zLTtiykXe5h60"
    ]
  },
  {
    "platform" : "IPHONE",
    "searchTime" : "2023-07-27T21:38:44.384Z[UTC]",
    "searchQuery" : "favor",
    "searchInteractionURIs" : [
    ]
  },
  {
    "platform" : "IPHONE_ARM64",
    "searchTime" : "2023-07-27T21:38:54.688Z[UTC]",
    "searchQuery" : "f",
    "searchInteractionURIs" : [
    ]
  },
  {
    "platform" : "IPHONE",
    "searchTime" : "2023-07-27T21:45:56.293Z[UTC]",
    "searchQuery" : "slut me ",
    "searchInteractionURIs" : [
      "spotify:track:5BmB3OaQyYXCqRyN8iR2Yi",
      "spotify:track:5BmB3OaQyYXCqRyN8iR2Yi"
    ]
  },
  {
    "platform" : "IPHONE",
    "searchTime" : "2023-07-27T22:03:38.633Z[UTC]",
    "searchQuery" : "ok com",
    "searchInteractionURIs" : [
      "spotify:album:0tzfI6NFJqcJkWb23R3lRZ"
    ]
  },
  {
    "platform" : "IPHONE",
    "searchTime" : "2023-07-28T03:59:53.895Z[UTC]",
    "searchQuery" : "tra",
    "searchInteractionURIs" : [
      "spotify:artist:0Y5tJX1MQlPlqiwlOH1tJY"
    ]
  },
  {
    "platform" : "IPHONE_ARM64",
    "searchTime" : "2023-07-28T04:00:18.184Z[UTC]",
    "searchQuery" : "utopia",
    "searchInteractionURIs" : [
    ]
  },
  {
    "platform" : "IPHONE",
    "searchTime" : "2023-07-28T04:00:26.440Z[UTC]",
    "searchQuery" : "utopia travis scott",
    "searchInteractionURIs" : [
    ]
  },
  {
    "platform" : "IPHONE",
    "searchTime" : "2023-07-28T04:00:57.430Z[UTC]",
    "searchQuery" : "Børns",
    "searchInteractionURIs" : [
      "spotify:artist:1KP6TWI40m7p3QBTU6u2xo"
    ]
  },
  {
    "platform" : "IPHONE",
    "searchTime" : "2023-07-28T04:01:11.811Z[UTC]",
    "searchQuery" : "post",
    "searchInteractionURIs" : [
      "spotify:artist:246dkjvS1zLTtiykXe5h60"
    ]
  },
  {
    "platform" : "IPHONE",
    "searchTime" : "2023-07-28T04:01:58.579Z[UTC]",
    "searchQuery" : "Børns",
    "searchInteractionURIs" : [
    ]
  },
  {
    "platform" : "IPHONE",
    "searchTime" : "2023-07-28T04:03:25.275Z[UTC]",
    "searchQuery" : "trav",
    "searchInteractionURIs" : [
    ]
  },
  {
    "platform" : "IPHONE",
    "searchTime" : "2023-07-28T04:04:45.382Z[UTC]",
    "searchQuery" : "suddenly bor",
    "searchInteractionURIs" : [
    ]
  },
  {
    "platform" : "IPHONE_ARM64",
    "searchTime" : "2023-07-28T04:15:52.123Z[UTC]",
    "searchQuery" : "new",
    "searchInteractionURIs" : [
    ]
  },
  {
    "platform" : "IPHONE",
    "searchTime" : "2023-07-28T04:16:03.946Z[UTC]",
    "searchQuery" : "new mus",
    "searchInteractionURIs" : [
      "spotify:playlist:37i9dQZEVXbgAH8UUfXzUE"
    ]
  },
  {
    "platform" : "IPHONE_ARM64",
    "searchTime" : "2023-07-28T20:15:45.315Z[UTC]",
    "searchQuery" : "au",
    "searchInteractionURIs" : [
    ]
  },
  {
    "platform" : "IPHONE_ARM64",
    "searchTime" : "2023-07-28T20:15:45.685Z[UTC]",
    "searchQuery" : "austi",
    "searchInteractionURIs" : [
    ]
  },
  {
    "platform" : "IPHONE",
    "searchTime" : "2023-07-28T20:50:55.826Z[UTC]",
    "searchQuery" : "austin",
    "searchInteractionURIs" : [
    ]
  },
  {
    "platform" : "IPHONE_ARM64",
    "searchTime" : "2023-07-28T21:23:54.371Z[UTC]",
    "searchQuery" : "utop",
    "searchInteractionURIs" : [
    ]
  },
  {
    "platform" : "IPHONE",
    "searchTime" : "2023-07-29T19:39:42.260Z[UTC]",
    "searchQuery" : "Børns",
    "searchInteractionURIs" : [
    ]
  },
  {
    "platform" : "IPHONE_ARM64",
    "searchTime" : "2023-07-31T01:04:33.138Z[UTC]",
    "searchQuery" : "aus",
    "searchInteractionURIs" : [
    ]
  },
  {
    "platform" : "IPHONE_ARM64",
    "searchTime" : "2023-07-31T04:35:44.927Z[UTC]",
    "searchQuery" : "m",
    "searchInteractionURIs" : [
    ]
  },
  {
    "platform" : "IPHONE",
    "searchTime" : "2023-08-01T16:15:43.789Z[UTC]",
    "searchQuery" : "strokes",
    "searchInteractionURIs" : [
    ]
  },
  {
    "platform" : "IPHONE_ARM64",
    "searchTime" : "2023-08-02T22:31:07.687Z[UTC]",
    "searchQuery" : "a",
    "searchInteractionURIs" : [
    ]
  },
  {
    "platform" : "IPHONE",
    "searchTime" : "2023-08-03T21:04:44.426Z[UTC]",
    "searchQuery" : "my eye",
    "searchInteractionURIs" : [
    ]
  },
  {
    "platform" : "IPHONE",
    "searchTime" : "2023-08-03T21:31:32.136Z[UTC]",
    "searchQuery" : "binch",
    "searchInteractionURIs" : [
    ]
  },
  {
    "platform" : "",
    "searchTime" : "2023-08-04T00:02:22.141Z[UTC]",
    "searchQuery" : "fuku",
    "searchInteractionURIs" : [
    ]
  },
  {
    "platform" : "IPHONE",
    "searchTime" : "2023-08-04T00:02:22.538Z[UTC]",
    "searchQuery" : "fuku",
    "searchInteractionURIs" : [
    ]
  },
  {
    "platform" : "",
    "searchTime" : "2023-08-04T00:02:24.664Z[UTC]",
    "searchQuery" : "t",
    "searchInteractionURIs" : [
    ]
  },
  {
    "platform" : "",
    "searchTime" : "2023-08-04T00:02:24.753Z[UTC]",
    "searchQuery" : "t",
    "searchInteractionURIs" : [
    ]
  },
  {
    "platform" : "",
    "searchTime" : "2023-08-04T00:02:24.795Z[UTC]",
    "searchQuery" : "tr",
    "searchInteractionURIs" : [
    ]
  },
  {
    "platform" : "",
    "searchTime" : "2023-08-04T00:02:24.922Z[UTC]",
    "searchQuery" : "tr",
    "searchInteractionURIs" : [
    ]
  },
  {
    "platform" : "",
    "searchTime" : "2023-08-04T00:02:25.025Z[UTC]",
    "searchQuery" : "tra",
    "searchInteractionURIs" : [
    ]
  },
  {
    "platform" : "",
    "searchTime" : "2023-08-04T00:02:25.082Z[UTC]",
    "searchQuery" : "tra",
    "searchInteractionURIs" : [
    ]
  },
  {
    "platform" : "",
    "searchTime" : "2023-08-04T00:02:25.126Z[UTC]",
    "searchQuery" : "trav",
    "searchInteractionURIs" : [
    ]
  },
  {
    "platform" : "",
    "searchTime" : "2023-08-04T00:02:25.198Z[UTC]",
    "searchQuery" : "trav",
    "searchInteractionURIs" : [
    ]
  },
  {
    "platform" : "IPHONE",
    "searchTime" : "2023-08-04T04:06:44.811Z[UTC]",
    "searchQuery" : "new",
    "searchInteractionURIs" : [
      "spotify:playlist:37i9dQZEVXbgAH8UUfXzUE"
    ]
  },
  {
    "platform" : "IPHONE_ARM64",
    "searchTime" : "2023-08-04T18:03:44.158Z[UTC]",
    "searchQuery" : "su",
    "searchInteractionURIs" : [
    ]
  },
  {
    "platform" : "IPHONE_ARM64",
    "searchTime" : "2023-08-04T18:03:46.594Z[UTC]",
    "searchQuery" : "super f",
    "searchInteractionURIs" : [
    ]
  },
  {
    "platform" : "IPHONE_ARM64",
    "searchTime" : "2023-08-04T22:38:17.246Z[UTC]",
    "searchQuery" : "the be",
    "searchInteractionURIs" : [
    ]
  },
  {
    "platform" : "IPHONE",
    "searchTime" : "2023-08-05T20:26:25.464Z[UTC]",
    "searchQuery" : "dj l",
    "searchInteractionURIs" : [
    ]
  },
  {
    "platform" : "IPHONE",
    "searchTime" : "2023-08-06T23:01:36.663Z[UTC]",
    "searchQuery" : "radi",
    "searchInteractionURIs" : [
    ]
  },
  {
    "platform" : "IPHONE",
    "searchTime" : "2023-08-06T23:02:00.833Z[UTC]",
    "searchQuery" : "taylor",
    "searchInteractionURIs" : [
      "spotify:artist:06HL4z0CvFAxyc27GXpf02"
    ]
  },
  {
    "platform" : "IPHONE_ARM64",
    "searchTime" : "2023-08-07T01:16:45.211Z[UTC]",
    "searchQuery" : "on re",
    "searchInteractionURIs" : [
    ]
  },
  {
    "platform" : "",
    "searchTime" : "2023-08-08T00:50:09.193Z[UTC]",
    "searchQuery" : "r",
    "searchInteractionURIs" : [
    ]
  },
  {
    "platform" : "",
    "searchTime" : "2023-08-08T00:50:09.278Z[UTC]",
    "searchQuery" : "rad",
    "searchInteractionURIs" : [
    ]
  },
  {
    "platform" : "",
    "searchTime" : "2023-08-08T00:50:09.278Z[UTC]",
    "searchQuery" : "ra",
    "searchInteractionURIs" : [
    ]
  },
  {
    "platform" : "",
    "searchTime" : "2023-08-08T00:50:09.282Z[UTC]",
    "searchQuery" : "r",
    "searchInteractionURIs" : [
    ]
  },
  {
    "platform" : "",
    "searchTime" : "2023-08-08T00:50:09.333Z[UTC]",
    "searchQuery" : "ra",
    "searchInteractionURIs" : [
    ]
  },
  {
    "platform" : "",
    "searchTime" : "2023-08-08T00:50:09.342Z[UTC]",
    "searchQuery" : "rad",
    "searchInteractionURIs" : [
    ]
  },
  {
    "platform" : "",
    "searchTime" : "2023-08-08T00:50:09.381Z[UTC]",
    "searchQuery" : "radi",
    "searchInteractionURIs" : [
    ]
  },
  {
    "platform" : "",
    "searchTime" : "2023-08-08T00:50:09.443Z[UTC]",
    "searchQuery" : "radi",
    "searchInteractionURIs" : [
    ]
  },
  {
    "platform" : "",
    "searchTime" : "2023-08-08T00:50:13.714Z[UTC]",
    "searchQuery" : "radio",
    "searchInteractionURIs" : [
    ]
  },
  {
    "platform" : "IPHONE_ARM64",
    "searchTime" : "2023-08-08T00:50:13.840Z[UTC]",
    "searchQuery" : "radio",
    "searchInteractionURIs" : [
    ]
  },
  {
    "platform" : "",
    "searchTime" : "2023-08-08T00:50:14.695Z[UTC]",
    "searchQuery" : "a",
    "searchInteractionURIs" : [
    ]
  },
  {
    "platform" : "",
    "searchTime" : "2023-08-08T00:50:14.759Z[UTC]",
    "searchQuery" : "a",
    "searchInteractionURIs" : [
    ]
  },
  {
    "platform" : "",
    "searchTime" : "2023-08-08T00:50:15.836Z[UTC]",
    "searchQuery" : "am",
    "searchInteractionURIs" : [
    ]
  },
  {
    "platform" : "",
    "searchTime" : "2023-08-08T00:50:15.879Z[UTC]",
    "searchQuery" : "am",
    "searchInteractionURIs" : [
    ]
  },
  {
    "platform" : "",
    "searchTime" : "2023-08-08T00:50:18.200Z[UTC]",
    "searchQuery" : "amne",
    "searchInteractionURIs" : [
    ]
  },
  {
    "platform" : "",
    "searchTime" : "2023-08-08T00:50:18.202Z[UTC]",
    "searchQuery" : "amn",
    "searchInteractionURIs" : [
    ]
  },
  {
    "platform" : "",
    "searchTime" : "2023-08-08T00:50:18.248Z[UTC]",
    "searchQuery" : "amn",
    "searchInteractionURIs" : [
    ]
  },
  {
    "platform" : "",
    "searchTime" : "2023-08-08T00:50:18.279Z[UTC]",
    "searchQuery" : "amne",
    "searchInteractionURIs" : [
    ]
  },
  {
    "platform" : "IPHONE_ARM64",
    "searchTime" : "2023-08-08T22:17:53.877Z[UTC]",
    "searchQuery" : "first",
    "searchInteractionURIs" : [
    ]
  },
  {
    "platform" : "IPHONE_ARM64",
    "searchTime" : "2023-08-08T22:17:53.917Z[UTC]",
    "searchQuery" : "first i",
    "searchInteractionURIs" : [
    ]
  },
  {
    "platform" : "IPHONE_ARM64",
    "searchTime" : "2023-08-08T22:17:55.026Z[UTC]",
    "searchQuery" : "f",
    "searchInteractionURIs" : [
    ]
  },
  {
    "platform" : "IPHONE_ARM64",
    "searchTime" : "2023-08-09T20:54:33.520Z[UTC]",
    "searchQuery" : "angle",
    "searchInteractionURIs" : [
    ]
  },
  {
    "platform" : "IPHONE",
    "searchTime" : "2023-08-10T17:23:43.919Z[UTC]",
    "searchQuery" : "carly",
    "searchInteractionURIs" : [
    ]
  },
  {
    "platform" : "IPHONE",
    "searchTime" : "2023-08-10T21:30:42.302Z[UTC]",
    "searchQuery" : "the lonel",
    "searchInteractionURIs" : [
      "spotify:track:6c6vULMrRuN4NECs2iB1xe"
    ]
  },
  {
    "platform" : "IPHONE_ARM64",
    "searchTime" : "2023-08-10T22:38:49.128Z[UTC]",
    "searchQuery" : "hard",
    "searchInteractionURIs" : [
    ]
  },
  {
    "platform" : "IPHONE",
    "searchTime" : "2023-08-10T22:38:49.572Z[UTC]",
    "searchQuery" : "hard to",
    "searchInteractionURIs" : [
      "spotify:track:0OM9ri37LIbPc9hffwsyb1"
    ]
  },
  {
    "platform" : "IPHONE_ARM64",
    "searchTime" : "2023-08-10T22:49:20.392Z[UTC]",
    "searchQuery" : "will you t",
    "searchInteractionURIs" : [
    ]
  },
  {
    "platform" : "IPHONE",
    "searchTime" : "2023-08-10T22:49:24.726Z[UTC]",
    "searchQuery" : "will you trpair my d",
    "searchInteractionURIs" : [
      "spotify:track:0qMkclbAhnpIojnfbgm29i"
    ]
  },
  {
    "platform" : "IPHONE_ARM64",
    "searchTime" : "2023-08-11T01:00:54.826Z[UTC]",
    "searchQuery" : "roo",
    "searchInteractionURIs" : [
    ]
  },
  {
    "platform" : "IPHONE",
    "searchTime" : "2023-08-11T04:20:19.779Z[UTC]",
    "searchQuery" : "room ",
    "searchInteractionURIs" : [
    ]
  },
  {
    "platform" : "IPHONE_ARM64",
    "searchTime" : "2023-08-11T17:59:43.994Z[UTC]",
    "searchQuery" : "summ",
    "searchInteractionURIs" : [
    ]
  },
  {
    "platform" : "IPHONE",
    "searchTime" : "2023-08-11T17:59:46.579Z[UTC]",
    "searchQuery" : "summer of",
    "searchInteractionURIs" : [
      "spotify:track:0GONea6G2XdnHWjNZd6zt3"
    ]
  },
  {
    "platform" : "IPHONE",
    "searchTime" : "2023-08-11T17:59:53.428Z[UTC]",
    "searchQuery" : "let do",
    "searchInteractionURIs" : [
      "spotify:track:1CeC8kOYxUTCC2wHGtWROD",
      "spotify:track:1CeC8kOYxUTCC2wHGtWROD"
    ]
  },
  {
    "platform" : "IPHONE_ARM64",
    "searchTime" : "2023-08-11T18:21:11.036Z[UTC]",
    "searchQuery" : "bad ",
    "searchInteractionURIs" : [
    ]
  },
  {
    "platform" : "IPHONE",
    "searchTime" : "2023-08-11T18:21:11.507Z[UTC]",
    "searchQuery" : "bad id",
    "searchInteractionURIs" : [
      "spotify:artist:1McMsnEElThX1knmY4oliG"
    ]
  },
  {
    "platform" : "IPHONE",
    "searchTime" : "2023-08-11T21:33:54.935Z[UTC]",
    "searchQuery" : "everyday",
    "searchInteractionURIs" : [
      "spotify:track:2VYqgye3Wf9ySE4qYM3iJn"
    ]
  },
  {
    "platform" : "IPHONE_ARM64",
    "searchTime" : "2023-08-12T21:02:42.935Z[UTC]",
    "searchQuery" : "b",
    "searchInteractionURIs" : [
    ]
  },
  {
    "platform" : "IPHONE_ARM64",
    "searchTime" : "2023-08-14T14:07:23.913Z[UTC]",
    "searchQuery" : "fr",
    "searchInteractionURIs" : [
    ]
  },
  {
    "platform" : "IPHONE",
    "searchTime" : "2023-08-14T14:07:33.763Z[UTC]",
    "searchQuery" : "fried egg",
    "searchInteractionURIs" : [
      "spotify:show:0jMFGCaFpcG0eKyOCNbb0T"
    ]
  },
  {
    "platform" : "IPHONE_ARM64",
    "searchTime" : "2023-08-14T21:35:19.534Z[UTC]",
    "searchQuery" : "i live",
    "searchInteractionURIs" : [
    ]
  },
  {
    "platform" : "IPHONE_ARM64",
    "searchTime" : "2023-08-14T21:35:19.627Z[UTC]",
    "searchQuery" : "i live you honey",
    "searchInteractionURIs" : [
    ]
  },
  {
    "platform" : "IPHONE_ARM64",
    "searchTime" : "2023-08-14T22:43:35.940Z[UTC]",
    "searchQuery" : "f",
    "searchInteractionURIs" : [
    ]
  },
  {
    "platform" : "IPHONE",
    "searchTime" : "2023-08-14T22:43:36.484Z[UTC]",
    "searchQuery" : "fuku",
    "searchInteractionURIs" : [
      "spotify:track:4rXLjWdF2ZZpXCVTfWcshS",
      "spotify:track:4rXLjWdF2ZZpXCVTfWcshS"
    ]
  },
  {
    "platform" : "",
    "searchTime" : "2023-08-15T00:51:04.900Z[UTC]",
    "searchQuery" : "h",
    "searchInteractionURIs" : [
    ]
  },
  {
    "platform" : "",
    "searchTime" : "2023-08-15T00:51:05.059Z[UTC]",
    "searchQuery" : "hu",
    "searchInteractionURIs" : [
    ]
  },
  {
    "platform" : "",
    "searchTime" : "2023-08-15T00:51:05.423Z[UTC]",
    "searchQuery" : "hub",
    "searchInteractionURIs" : [
    ]
  },
  {
    "platform" : "",
    "searchTime" : "2023-08-15T00:51:05.492Z[UTC]",
    "searchQuery" : "hube",
    "searchInteractionURIs" : [
    ]
  },
  {
    "platform" : "",
    "searchTime" : "2023-08-15T00:51:05.660Z[UTC]",
    "searchQuery" : "huber",
    "searchInteractionURIs" : [
    ]
  },
  {
    "platform" : "IPHONE",
    "searchTime" : "2023-08-15T01:01:00.010Z[UTC]",
    "searchQuery" : "huber",
    "searchInteractionURIs" : [
    ]
  },
  {
    "platform" : "IPHONE_ARM64",
    "searchTime" : "2023-08-15T01:01:17.549Z[UTC]",
    "searchQuery" : "analyti",
    "searchInteractionURIs" : [
    ]
  },
  {
    "platform" : "IPHONE_ARM64",
    "searchTime" : "2023-08-15T01:20:52.229Z[UTC]",
    "searchQuery" : "p",
    "searchInteractionURIs" : [
    ]
  },
  {
    "platform" : "IPHONE",
    "searchTime" : "2023-08-15T01:20:52.805Z[UTC]",
    "searchQuery" : "pyr",
    "searchInteractionURIs" : [
      "spotify:track:0tfvDUmADEEEqrPcRJNT29"
    ]
  },
  {
    "platform" : "IPHONE_ARM64",
    "searchTime" : "2023-08-15T17:23:02.437Z[UTC]",
    "searchQuery" : "ch",
    "searchInteractionURIs" : [
    ]
  },
  {
    "platform" : "IPHONE_ARM64",
    "searchTime" : "2023-08-15T17:23:03.238Z[UTC]",
    "searchQuery" : "choice",
    "searchInteractionURIs" : [
    ]
  },
  {
    "platform" : "IPHONE",
    "searchTime" : "2023-08-15T23:00:15.894Z[UTC]",
    "searchQuery" : "oxyto",
    "searchInteractionURIs" : [
    ]
  },
  {
    "platform" : "",
    "searchTime" : "2023-08-16T00:48:51.281Z[UTC]",
    "searchQuery" : "l",
    "searchInteractionURIs" : [
    ]
  },
  {
    "platform" : "",
    "searchTime" : "2023-08-16T00:48:51.358Z[UTC]",
    "searchQuery" : "l",
    "searchInteractionURIs" : [
    ]
  },
  {
    "platform" : "",
    "searchTime" : "2023-08-16T00:48:52.977Z[UTC]",
    "searchQuery" : "g",
    "searchInteractionURIs" : [
    ]
  },
  {
    "platform" : "",
    "searchTime" : "2023-08-16T00:48:53.043Z[UTC]",
    "searchQuery" : "gr",
    "searchInteractionURIs" : [
    ]
  },
  {
    "platform" : "",
    "searchTime" : "2023-08-16T00:48:53.046Z[UTC]",
    "searchQuery" : "g",
    "searchInteractionURIs" : [
    ]
  },
  {
    "platform" : "",
    "searchTime" : "2023-08-16T00:48:53.098Z[UTC]",
    "searchQuery" : "gr",
    "searchInteractionURIs" : [
    ]
  },
  {
    "platform" : "",
    "searchTime" : "2023-08-16T00:48:53.281Z[UTC]",
    "searchQuery" : "gra",
    "searchInteractionURIs" : [
    ]
  },
  {
    "platform" : "",
    "searchTime" : "2023-08-16T00:48:53.349Z[UTC]",
    "searchQuery" : "gra",
    "searchInteractionURIs" : [
    ]
  },
  {
    "platform" : "",
    "searchTime" : "2023-08-16T00:48:53.420Z[UTC]",
    "searchQuery" : "grac",
    "searchInteractionURIs" : [
    ]
  },
  {
    "platform" : "",
    "searchTime" : "2023-08-16T00:48:53.422Z[UTC]",
    "searchQuery" : "grace",
    "searchInteractionURIs" : [
    ]
  },
  {
    "platform" : "",
    "searchTime" : "2023-08-16T00:48:53.501Z[UTC]",
    "searchQuery" : "grace",
    "searchInteractionURIs" : [
    ]
  },
  {
    "platform" : "",
    "searchTime" : "2023-08-16T00:48:53.504Z[UTC]",
    "searchQuery" : "grace ",
    "searchInteractionURIs" : [
    ]
  },
  {
    "platform" : "",
    "searchTime" : "2023-08-16T00:48:53.511Z[UTC]",
    "searchQuery" : "grac",
    "searchInteractionURIs" : [
    ]
  },
  {
    "platform" : "",
    "searchTime" : "2023-08-16T00:48:53.554Z[UTC]",
    "searchQuery" : "grace ",
    "searchInteractionURIs" : [
    ]
  },
  {
    "platform" : "",
    "searchTime" : "2023-08-16T00:48:53.769Z[UTC]",
    "searchQuery" : "grace j",
    "searchInteractionURIs" : [
    ]
  },
  {
    "platform" : "",
    "searchTime" : "2023-08-16T00:48:53.824Z[UTC]",
    "searchQuery" : "grace j",
    "searchInteractionURIs" : [
    ]
  },
  {
    "platform" : "",
    "searchTime" : "2023-08-16T00:48:53.908Z[UTC]",
    "searchQuery" : "grace je",
    "searchInteractionURIs" : [
    ]
  },
  {
    "platform" : "",
    "searchTime" : "2023-08-16T00:48:53.952Z[UTC]",
    "searchQuery" : "grace je",
    "searchInteractionURIs" : [
    ]
  },
  {
    "platform" : "",
    "searchTime" : "2023-08-16T00:48:54.037Z[UTC]",
    "searchQuery" : "grace jef",
    "searchInteractionURIs" : [
    ]
  },
  {
    "platform" : "IPHONE_ARM64",
    "searchTime" : "2023-08-16T00:48:54.258Z[UTC]",
    "searchQuery" : "grace jef",
    "searchInteractionURIs" : [
    ]
  },
  {
    "platform" : "",
    "searchTime" : "2023-08-16T00:48:54.283Z[UTC]",
    "searchQuery" : "grace jeff",
    "searchInteractionURIs" : [
    ]
  },
  {
    "platform" : "",
    "searchTime" : "2023-08-16T00:48:54.399Z[UTC]",
    "searchQuery" : "grace jeff",
    "searchInteractionURIs" : [
    ]
  },
  {
    "platform" : "IPHONE",
    "searchTime" : "2023-08-16T16:40:41.698Z[UTC]",
    "searchQuery" : "death",
    "searchInteractionURIs" : [
    ]
  },
  {
    "platform" : "IPHONE_ARM64",
    "searchTime" : "2023-08-17T17:33:47.492Z[UTC]",
    "searchQuery" : "certi",
    "searchInteractionURIs" : [
    ]
  },
  {
    "platform" : "",
    "searchTime" : "2023-08-17T22:03:08.206Z[UTC]",
    "searchQuery" : "Is this it",
    "searchInteractionURIs" : [
    ]
  },
  {
    "platform" : "IPHONE_ARM64",
    "searchTime" : "2023-08-17T22:39:11.966Z[UTC]",
    "searchQuery" : "nig",
    "searchInteractionURIs" : [
    ]
  },
  {
    "platform" : "IPHONE_ARM64",
    "searchTime" : "2023-08-17T22:39:12.641Z[UTC]",
    "searchQuery" : "nightc",
    "searchInteractionURIs" : [
    ]
  },
  {
    "platform" : "IPHONE_ARM64",
    "searchTime" : "2023-08-18T01:06:27.225Z[UTC]",
    "searchQuery" : "th",
    "searchInteractionURIs" : [
    ]
  },
  {
    "platform" : "IPHONE_ARM64",
    "searchTime" : "2023-08-18T17:22:47.773Z[UTC]",
    "searchQuery" : "u",
    "searchInteractionURIs" : [
    ]
  },
  {
    "platform" : "IPHONE",
    "searchTime" : "2023-08-18T18:12:02.401Z[UTC]",
    "searchQuery" : "uto",
    "searchInteractionURIs" : [
    ]
  },
  {
    "platform" : "IPHONE",
    "searchTime" : "2023-08-18T19:03:52.145Z[UTC]",
    "searchQuery" : "rele",
    "searchInteractionURIs" : [
    ]
  },
  {
    "platform" : "IPHONE_ARM64",
    "searchTime" : "2023-08-18T19:04:53.864Z[UTC]",
    "searchQuery" : "jo",
    "searchInteractionURIs" : [
    ]
  },
  {
    "platform" : "IPHONE",
    "searchTime" : "2023-08-18T19:04:53.962Z[UTC]",
    "searchQuery" : "joe",
    "searchInteractionURIs" : [
      "spotify:show:4rOoJ6Egrf8K2IrywzwOMk",
      "spotify:show:4rOoJ6Egrf8K2IrywzwOMk"
    ]
  },
  {
    "platform" : "IPHONE",
    "searchTime" : "2023-08-19T22:07:44.274Z[UTC]",
    "searchQuery" : "ice soic",
    "searchInteractionURIs" : [
    ]
  },
  {
    "platform" : "IPHONE_ARM64",
    "searchTime" : "2023-08-19T22:07:46.633Z[UTC]",
    "searchQuery" : "ji",
    "searchInteractionURIs" : [
    ]
  },
  {
    "platform" : "IPHONE",
    "searchTime" : "2023-08-19T22:14:50.063Z[UTC]",
    "searchQuery" : "dra",
    "searchInteractionURIs" : [
    ]
  },
  {
    "platform" : "IPHONE_ARM64",
    "searchTime" : "2023-08-19T22:14:52.366Z[UTC]",
    "searchQuery" : "life",
    "searchInteractionURIs" : [
    ]
  },
  {
    "platform" : "IPHONE",
    "searchTime" : "2023-08-19T22:23:06.037Z[UTC]",
    "searchQuery" : "life is",
    "searchInteractionURIs" : [
    ]
  },
  {
    "platform" : "IPHONE",
    "searchTime" : "2023-08-21T16:11:34.518Z[UTC]",
    "searchQuery" : "web analy",
    "searchInteractionURIs" : [
      "spotify:episode:5eobcIiBfM2B6ryfbadshq"
    ]
  },
  {
    "platform" : "IPHONE",
    "searchTime" : "2023-08-22T19:32:16.429Z[UTC]",
    "searchQuery" : "the lone",
    "searchInteractionURIs" : [
    ]
  },
  {
    "platform" : "IPHONE_ARM64",
    "searchTime" : "2023-08-22T22:01:44.663Z[UTC]",
    "searchQuery" : "c",
    "searchInteractionURIs" : [
    ]
  },
  {
    "platform" : "IPHONE_ARM64",
    "searchTime" : "2023-08-24T01:20:18.796Z[UTC]",
    "searchQuery" : "12",
    "searchInteractionURIs" : [
    ]
  },
  {
    "platform" : "IPHONE",
    "searchTime" : "2023-08-24T01:30:28.399Z[UTC]",
    "searchQuery" : "let",
    "searchInteractionURIs" : [
      "spotify:playlist:3hAf4id0adziQWUoenqOzS"
    ]
  },
  {
    "platform" : "IPHONE_ARM64",
    "searchTime" : "2023-08-24T17:13:39.472Z[UTC]",
    "searchQuery" : "tgecs",
    "searchInteractionURIs" : [
    ]
  },
  {
    "platform" : "WIN32_X86_64",
    "searchTime" : "2023-08-24T20:07:54.918Z[UTC]",
    "searchQuery" : "jon stewa",
    "searchInteractionURIs" : [
    ]
  },
  {
    "platform" : "IPHONE",
    "searchTime" : "2023-08-24T22:57:33.092Z[UTC]",
    "searchQuery" : "back 9",
    "searchInteractionURIs" : [
    ]
  },
  {
    "platform" : "IPHONE_ARM64",
    "searchTime" : "2023-08-24T22:57:35.636Z[UTC]",
    "searchQuery" : "one o",
    "searchInteractionURIs" : [
    ]
  },
  {
    "platform" : "",
    "searchTime" : "2023-08-25T00:29:26.434Z[UTC]",
    "searchQuery" : "t",
    "searchInteractionURIs" : [
    ]
  },
  {
    "platform" : "",
    "searchTime" : "2023-08-25T00:29:26.508Z[UTC]",
    "searchQuery" : "t",
    "searchInteractionURIs" : [
    ]
  },
  {
    "platform" : "",
    "searchTime" : "2023-08-25T00:29:26.660Z[UTC]",
    "searchQuery" : "tw",
    "searchInteractionURIs" : [
    ]
  },
  {
    "platform" : "",
    "searchTime" : "2023-08-25T00:29:26.712Z[UTC]",
    "searchQuery" : "tw",
    "searchInteractionURIs" : [
    ]
  },
  {
    "platform" : "",
    "searchTime" : "2023-08-25T00:29:26.939Z[UTC]",
    "searchQuery" : "two",
    "searchInteractionURIs" : [
    ]
  },
  {
    "platform" : "",
    "searchTime" : "2023-08-25T00:29:26.986Z[UTC]",
    "searchQuery" : "two",
    "searchInteractionURIs" : [
    ]
  },
  {
    "platform" : "",
    "searchTime" : "2023-08-25T00:29:41.524Z[UTC]",
    "searchQuery" : "t",
    "searchInteractionURIs" : [
    ]
  },
  {
    "platform" : "",
    "searchTime" : "2023-08-25T00:29:41.594Z[UTC]",
    "searchQuery" : "t",
    "searchInteractionURIs" : [
    ]
  },
  {
    "platform" : "",
    "searchTime" : "2023-08-25T00:29:41.728Z[UTC]",
    "searchQuery" : "tw",
    "searchInteractionURIs" : [
    ]
  },
  {
    "platform" : "",
    "searchTime" : "2023-08-25T00:29:41.785Z[UTC]",
    "searchQuery" : "tw",
    "searchInteractionURIs" : [
    ]
  },
  {
    "platform" : "",
    "searchTime" : "2023-08-25T00:29:41.796Z[UTC]",
    "searchQuery" : "two",
    "searchInteractionURIs" : [
    ]
  },
  {
    "platform" : "IPHONE_ARM64",
    "searchTime" : "2023-08-25T00:29:41.939Z[UTC]",
    "searchQuery" : "two",
    "searchInteractionURIs" : [
    ]
  },
  {
    "platform" : "",
    "searchTime" : "2023-08-25T00:29:42.071Z[UTC]",
    "searchQuery" : "two ",
    "searchInteractionURIs" : [
    ]
  },
  {
    "platform" : "",
    "searchTime" : "2023-08-25T00:29:42.134Z[UTC]",
    "searchQuery" : "two ",
    "searchInteractionURIs" : [
    ]
  },
  {
    "platform" : "",
    "searchTime" : "2023-08-25T00:29:42.239Z[UTC]",
    "searchQuery" : "two h",
    "searchInteractionURIs" : [
    ]
  },
  {
    "platform" : "",
    "searchTime" : "2023-08-25T00:29:42.320Z[UTC]",
    "searchQuery" : "two h",
    "searchInteractionURIs" : [
    ]
  },
  {
    "platform" : "",
    "searchTime" : "2023-08-25T00:29:42.428Z[UTC]",
    "searchQuery" : "two ho",
    "searchInteractionURIs" : [
    ]
  },
  {
    "platform" : "",
    "searchTime" : "2023-08-25T00:29:42.472Z[UTC]",
    "searchQuery" : "two ho",
    "searchInteractionURIs" : [
    ]
  },
  {
    "platform" : "",
    "searchTime" : "2023-08-25T00:29:42.624Z[UTC]",
    "searchQuery" : "two hot",
    "searchInteractionURIs" : [
    ]
  },
  {
    "platform" : "IPHONE",
    "searchTime" : "2023-08-25T00:35:24.292Z[UTC]",
    "searchQuery" : "two hot",
    "searchInteractionURIs" : [
    ]
  },
  {
    "platform" : "",
    "searchTime" : "2023-08-25T00:35:25.891Z[UTC]",
    "searchQuery" : "c",
    "searchInteractionURIs" : [
    ]
  },
  {
    "platform" : "",
    "searchTime" : "2023-08-25T00:35:25.998Z[UTC]",
    "searchQuery" : "c",
    "searchInteractionURIs" : [
    ]
  },
  {
    "platform" : "",
    "searchTime" : "2023-08-25T00:35:26.128Z[UTC]",
    "searchQuery" : "ci",
    "searchInteractionURIs" : [
    ]
  },
  {
    "platform" : "",
    "searchTime" : "2023-08-25T00:35:26.165Z[UTC]",
    "searchQuery" : "cig",
    "searchInteractionURIs" : [
    ]
  },
  {
    "platform" : "",
    "searchTime" : "2023-08-25T00:35:26.172Z[UTC]",
    "searchQuery" : "ci",
    "searchInteractionURIs" : [
    ]
  },
  {
    "platform" : "",
    "searchTime" : "2023-08-25T00:35:26.212Z[UTC]",
    "searchQuery" : "cig",
    "searchInteractionURIs" : [
    ]
  },
  {
    "platform" : "",
    "searchTime" : "2023-08-25T00:35:29.140Z[UTC]",
    "searchQuery" : "ciga",
    "searchInteractionURIs" : [
    ]
  },
  {
    "platform" : "",
    "searchTime" : "2023-08-25T00:35:29.191Z[UTC]",
    "searchQuery" : "ciga",
    "searchInteractionURIs" : [
    ]
  },
  {
    "platform" : "",
    "searchTime" : "2023-08-25T00:35:30.245Z[UTC]",
    "searchQuery" : "cigar",
    "searchInteractionURIs" : [
    ]
  },
  {
    "platform" : "",
    "searchTime" : "2023-08-25T00:35:30.296Z[UTC]",
    "searchQuery" : "cigar",
    "searchInteractionURIs" : [
    ]
  },
  {
    "platform" : "",
    "searchTime" : "2023-08-25T00:35:31.607Z[UTC]",
    "searchQuery" : "cigare",
    "searchInteractionURIs" : [
    ]
  },
  {
    "platform" : "",
    "searchTime" : "2023-08-25T00:35:31.657Z[UTC]",
    "searchQuery" : "cigare",
    "searchInteractionURIs" : [
    ]
  },
  {
    "platform" : "",
    "searchTime" : "2023-08-25T00:35:32.368Z[UTC]",
    "searchQuery" : "cigaret",
    "searchInteractionURIs" : [
    ]
  },
  {
    "platform" : "",
    "searchTime" : "2023-08-25T00:35:32.425Z[UTC]",
    "searchQuery" : "cigaret",
    "searchInteractionURIs" : [
    ]
  },
  {
    "platform" : "",
    "searchTime" : "2023-08-25T00:35:32.520Z[UTC]",
    "searchQuery" : "cigarett",
    "searchInteractionURIs" : [
    ]
  },
  {
    "platform" : "",
    "searchTime" : "2023-08-25T00:35:32.563Z[UTC]",
    "searchQuery" : "cigarett",
    "searchInteractionURIs" : [
    ]
  },
  {
    "platform" : "",
    "searchTime" : "2023-08-25T00:35:32.663Z[UTC]",
    "searchQuery" : "cigarette",
    "searchInteractionURIs" : [
    ]
  },
  {
    "platform" : "",
    "searchTime" : "2023-08-25T00:35:32.746Z[UTC]",
    "searchQuery" : "cigarette",
    "searchInteractionURIs" : [
    ]
  },
  {
    "platform" : "",
    "searchTime" : "2023-08-25T00:35:32.935Z[UTC]",
    "searchQuery" : "cigarettes ",
    "searchInteractionURIs" : [
    ]
  },
  {
    "platform" : "",
    "searchTime" : "2023-08-25T00:35:32.936Z[UTC]",
    "searchQuery" : "cigarettes",
    "searchInteractionURIs" : [
    ]
  },
  {
    "platform" : "",
    "searchTime" : "2023-08-25T00:35:32.994Z[UTC]",
    "searchQuery" : "cigarettes ",
    "searchInteractionURIs" : [
    ]
  },
  {
    "platform" : "",
    "searchTime" : "2023-08-25T00:35:32.996Z[UTC]",
    "searchQuery" : "cigarettes",
    "searchInteractionURIs" : [
    ]
  },
  {
    "platform" : "",
    "searchTime" : "2023-08-25T00:35:33.066Z[UTC]",
    "searchQuery" : "cigarettes a",
    "searchInteractionURIs" : [
    ]
  },
  {
    "platform" : "",
    "searchTime" : "2023-08-25T00:35:33.133Z[UTC]",
    "searchQuery" : "cigarettes a",
    "searchInteractionURIs" : [
    ]
  },
  {
    "platform" : "",
    "searchTime" : "2023-08-25T00:35:33.455Z[UTC]",
    "searchQuery" : "cigarettes agt",
    "searchInteractionURIs" : [
    ]
  },
  {
    "platform" : "",
    "searchTime" : "2023-08-25T00:35:33.459Z[UTC]",
    "searchQuery" : "cigarettes ag",
    "searchInteractionURIs" : [
    ]
  },
  {
    "platform" : "",
    "searchTime" : "2023-08-25T00:35:33.514Z[UTC]",
    "searchQuery" : "cigarettes ag",
    "searchInteractionURIs" : [
    ]
  },
  {
    "platform" : "",
    "searchTime" : "2023-08-25T00:35:33.555Z[UTC]",
    "searchQuery" : "cigarettes agt",
    "searchInteractionURIs" : [
    ]
  },
  {
    "platform" : "",
    "searchTime" : "2023-08-25T00:35:33.618Z[UTC]",
    "searchQuery" : "cigarettes agte",
    "searchInteractionURIs" : [
    ]
  },
  {
    "platform" : "",
    "searchTime" : "2023-08-25T00:35:33.674Z[UTC]",
    "searchQuery" : "cigarettes agte",
    "searchInteractionURIs" : [
    ]
  },
  {
    "platform" : "",
    "searchTime" : "2023-08-25T00:35:33.851Z[UTC]",
    "searchQuery" : "cigarettes agter",
    "searchInteractionURIs" : [
    ]
  },
  {
    "platform" : "",
    "searchTime" : "2023-08-25T00:35:33.877Z[UTC]",
    "searchQuery" : "cigarettes agter",
    "searchInteractionURIs" : [
    ]
  },
  {
    "platform" : "",
    "searchTime" : "2023-08-25T00:35:33.962Z[UTC]",
    "searchQuery" : "cigarettes agter ",
    "searchInteractionURIs" : [
    ]
  },
  {
    "platform" : "",
    "searchTime" : "2023-08-25T00:35:34.031Z[UTC]",
    "searchQuery" : "cigarettes agter ",
    "searchInteractionURIs" : [
    ]
  },
  {
    "platform" : "",
    "searchTime" : "2023-08-25T00:35:34.038Z[UTC]",
    "searchQuery" : "cigarettes agter s",
    "searchInteractionURIs" : [
    ]
  },
  {
    "platform" : "",
    "searchTime" : "2023-08-25T00:35:34.106Z[UTC]",
    "searchQuery" : "cigarettes agter s",
    "searchInteractionURIs" : [
    ]
  },
  {
    "platform" : "",
    "searchTime" : "2023-08-25T00:35:34.853Z[UTC]",
    "searchQuery" : "cigarettes agter se",
    "searchInteractionURIs" : [
    ]
  },
  {
    "platform" : "",
    "searchTime" : "2023-08-25T00:35:35.048Z[UTC]",
    "searchQuery" : "cigarettes agter sex",
    "searchInteractionURIs" : [
    ]
  },
  {
    "platform" : "",
    "searchTime" : "2023-08-25T00:35:35.097Z[UTC]",
    "searchQuery" : "cigarettes agter sex",
    "searchInteractionURIs" : [
    ]
  },
  {
    "platform" : "IPHONE_ARM64",
    "searchTime" : "2023-08-25T00:35:35.123Z[UTC]",
    "searchQuery" : "cigarettes agter se",
    "searchInteractionURIs" : [
    ]
  },
  {
    "platform" : "",
    "searchTime" : "2023-08-25T00:35:35.238Z[UTC]",
    "searchQuery" : "cigarettes agter sex ",
    "searchInteractionURIs" : [
    ]
  },
  {
    "platform" : "",
    "searchTime" : "2023-08-25T00:35:35.319Z[UTC]",
    "searchQuery" : "cigarettes agter sex ",
    "searchInteractionURIs" : [
    ]
  },
  {
    "platform" : "",
    "searchTime" : "2023-08-25T00:35:35.330Z[UTC]",
    "searchQuery" : "cigarettes agter sex s",
    "searchInteractionURIs" : [
    ]
  },
  {
    "platform" : "",
    "searchTime" : "2023-08-25T00:35:35.397Z[UTC]",
    "searchQuery" : "cigarettes agter sex s",
    "searchInteractionURIs" : [
    ]
  },
  {
    "platform" : "",
    "searchTime" : "2023-08-25T00:35:35.522Z[UTC]",
    "searchQuery" : "cigarettes agter sex se",
    "searchInteractionURIs" : [
    ]
  },
  {
    "platform" : "",
    "searchTime" : "2023-08-25T00:35:35.595Z[UTC]",
    "searchQuery" : "cigarettes agter sex se",
    "searchInteractionURIs" : [
    ]
  },
  {
    "platform" : "",
    "searchTime" : "2023-08-25T00:35:35.706Z[UTC]",
    "searchQuery" : "cigarettes agter sex set",
    "searchInteractionURIs" : [
    ]
  },
  {
    "platform" : "",
    "searchTime" : "2023-08-25T00:35:35.786Z[UTC]",
    "searchQuery" : "cigarettes agter sex set",
    "searchInteractionURIs" : [
    ]
  },
  {
    "platform" : "",
    "searchTime" : "2023-08-25T00:35:37.858Z[UTC]",
    "searchQuery" : "cigarettes agter sex se",
    "searchInteractionURIs" : [
    ]
  },
  {
    "platform" : "",
    "searchTime" : "2023-08-25T00:35:37.889Z[UTC]",
    "searchQuery" : "cigarettes agter sex se",
    "searchInteractionURIs" : [
    ]
  },
  {
    "platform" : "",
    "searchTime" : "2023-08-25T00:35:37.972Z[UTC]",
    "searchQuery" : "cigarettes agter sex s",
    "searchInteractionURIs" : [
    ]
  },
  {
    "platform" : "",
    "searchTime" : "2023-08-25T00:35:38.028Z[UTC]",
    "searchQuery" : "cigarettes agter sex s",
    "searchInteractionURIs" : [
    ]
  },
  {
    "platform" : "",
    "searchTime" : "2023-08-25T00:35:38.167Z[UTC]",
    "searchQuery" : "cigarettes agter sex ",
    "searchInteractionURIs" : [
    ]
  },
  {
    "platform" : "",
    "searchTime" : "2023-08-25T00:35:38.184Z[UTC]",
    "searchQuery" : "cigarettes agter sex ",
    "searchInteractionURIs" : [
    ]
  },
  {
    "platform" : "",
    "searchTime" : "2023-08-25T00:35:38.355Z[UTC]",
    "searchQuery" : "cigarettes agter sex",
    "searchInteractionURIs" : [
    ]
  },
  {
    "platform" : "IPHONE",
    "searchTime" : "2023-08-25T00:35:48.443Z[UTC]",
    "searchQuery" : "cigarettes agter sex",
    "searchInteractionURIs" : [
      "spotify:playlist:2GQaKjIVenHODzB3igZdzj",
      "spotify:playlist:4oSLOBQVHNFItpEhKeVbPC"
    ]
  },
  {
    "platform" : "IPHONE",
    "searchTime" : "2023-08-25T04:01:12.634Z[UTC]",
    "searchQuery" : "dra",
    "searchInteractionURIs" : [
      "spotify:artist:3TVXtAsR1Inumwj472S9r4"
    ]
  },
  {
    "platform" : "IPHONE",
    "searchTime" : "2023-08-25T04:02:36.982Z[UTC]",
    "searchQuery" : "zach",
    "searchInteractionURIs" : [
      "spotify:artist:40ZNYROS4zLfyyBSs2PGe2"
    ]
  },
  {
    "platform" : "IPHONE_ARM64",
    "searchTime" : "2023-08-25T04:04:30.863Z[UTC]",
    "searchQuery" : "r",
    "searchInteractionURIs" : [
    ]
  },
  {
    "platform" : "IPHONE",
    "searchTime" : "2023-08-25T04:04:48.828Z[UTC]",
    "searchQuery" : "new",
    "searchInteractionURIs" : [
      "spotify:playlist:37i9dQZF1DX4JAvHpjipBk"
    ]
  },
  {
    "platform" : "IPHONE",
    "searchTime" : "2023-08-25T04:09:57.695Z[UTC]",
    "searchQuery" : "dr",
    "searchInteractionURIs" : [
    ]
  },
  {
    "platform" : "IPHONE_ARM64",
    "searchTime" : "2023-08-25T11:54:11.873Z[UTC]",
    "searchQuery" : "d",
    "searchInteractionURIs" : [
    ]
  },
  {
    "platform" : "IPHONE",
    "searchTime" : "2023-08-25T11:54:12.441Z[UTC]",
    "searchQuery" : "drs",
    "searchInteractionURIs" : [
      "spotify:artist:3TVXtAsR1Inumwj472S9r4"
    ]
  },
  {
    "platform" : "IPHONE_ARM64",
    "searchTime" : "2023-08-25T14:57:55.707Z[UTC]",
    "searchQuery" : "hone",
    "searchInteractionURIs" : [
    ]
  },
  {
    "platform" : "IPHONE",
    "searchTime" : "2023-08-25T14:57:56.346Z[UTC]",
    "searchQuery" : "honestly",
    "searchInteractionURIs" : [
      "spotify:album:3cf4iSSKd8ffTncbtKljXw"
    ]
  },
  {
    "platform" : "IPHONE",
    "searchTime" : "2023-08-25T17:12:19.876Z[UTC]",
    "searchQuery" : "in ra",
    "searchInteractionURIs" : [
      "spotify:album:5vkqYmiPBYLaalcmjujWxK"
    ]
  },
  {
    "platform" : "IPHONE",
    "searchTime" : "2023-08-25T23:58:05.580Z[UTC]",
    "searchQuery" : "analyt",
    "searchInteractionURIs" : [
      "spotify:show:2ReJKUbDtcom5U0GgpOlAz"
    ]
  },
  {
    "platform" : "",
    "searchTime" : "2023-08-26T00:24:28.135Z[UTC]",
    "searchQuery" : "z",
    "searchInteractionURIs" : [
    ]
  },
  {
    "platform" : "",
    "searchTime" : "2023-08-26T00:24:28.162Z[UTC]",
    "searchQuery" : "z",
    "searchInteractionURIs" : [
    ]
  },
  {
    "platform" : "",
    "searchTime" : "2023-08-26T00:24:28.322Z[UTC]",
    "searchQuery" : "za",
    "searchInteractionURIs" : [
    ]
  },
  {
    "platform" : "",
    "searchTime" : "2023-08-26T00:24:28.380Z[UTC]",
    "searchQuery" : "za",
    "searchInteractionURIs" : [
    ]
  },
  {
    "platform" : "",
    "searchTime" : "2023-08-26T00:24:28.817Z[UTC]",
    "searchQuery" : "zac",
    "searchInteractionURIs" : [
    ]
  },
  {
    "platform" : "",
    "searchTime" : "2023-08-26T00:24:28.865Z[UTC]",
    "searchQuery" : "zac",
    "searchInteractionURIs" : [
    ]
  },
  {
    "platform" : "",
    "searchTime" : "2023-08-26T00:24:29.069Z[UTC]",
    "searchQuery" : "zach",
    "searchInteractionURIs" : [
    ]
  },
  {
    "platform" : "IPHONE",
    "searchTime" : "2023-08-26T00:24:29.437Z[UTC]",
    "searchQuery" : "zach",
    "searchInteractionURIs" : [
      "spotify:artist:40ZNYROS4zLfyyBSs2PGe2"
    ]
  },
  {
    "platform" : "",
    "searchTime" : "2023-08-26T00:58:09.282Z[UTC]",
    "searchQuery" : "c",
    "searchInteractionURIs" : [
    ]
  },
  {
    "platform" : "",
    "searchTime" : "2023-08-26T00:58:09.338Z[UTC]",
    "searchQuery" : "c",
    "searchInteractionURIs" : [
    ]
  },
  {
    "platform" : "",
    "searchTime" : "2023-08-26T00:58:09.410Z[UTC]",
    "searchQuery" : "ch",
    "searchInteractionURIs" : [
    ]
  },
  {
    "platform" : "",
    "searchTime" : "2023-08-26T00:58:09.470Z[UTC]",
    "searchQuery" : "ch",
    "searchInteractionURIs" : [
    ]
  },
  {
    "platform" : "",
    "searchTime" : "2023-08-26T00:58:09.711Z[UTC]",
    "searchQuery" : "cha",
    "searchInteractionURIs" : [
    ]
  },
  {
    "platform" : "",
    "searchTime" : "2023-08-26T00:58:09.775Z[UTC]",
    "searchQuery" : "cha",
    "searchInteractionURIs" : [
    ]
  },
  {
    "platform" : "",
    "searchTime" : "2023-08-26T00:58:09.934Z[UTC]",
    "searchQuery" : "char",
    "searchInteractionURIs" : [
    ]
  },
  {
    "platform" : "IPHONE_ARM64",
    "searchTime" : "2023-08-26T00:58:10.079Z[UTC]",
    "searchQuery" : "char",
    "searchInteractionURIs" : [
    ]
  },
  {
    "platform" : "",
    "searchTime" : "2023-08-26T00:58:10.917Z[UTC]",
    "searchQuery" : "charl",
    "searchInteractionURIs" : [
    ]
  },
  {
    "platform" : "",
    "searchTime" : "2023-08-26T00:58:10.972Z[UTC]",
    "searchQuery" : "charl",
    "searchInteractionURIs" : [
    ]
  },
  {
    "platform" : "",
    "searchTime" : "2023-08-26T00:58:12.242Z[UTC]",
    "searchQuery" : "charle",
    "searchInteractionURIs" : [
    ]
  },
  {
    "platform" : "",
    "searchTime" : "2023-08-26T00:58:12.320Z[UTC]",
    "searchQuery" : "charle",
    "searchInteractionURIs" : [
    ]
  },
  {
    "platform" : "",
    "searchTime" : "2023-08-26T00:58:12.419Z[UTC]",
    "searchQuery" : "charles",
    "searchInteractionURIs" : [
    ]
  },
  {
    "platform" : "",
    "searchTime" : "2023-08-26T00:58:12.483Z[UTC]",
    "searchQuery" : "charles",
    "searchInteractionURIs" : [
    ]
  },
  {
    "platform" : "",
    "searchTime" : "2023-08-26T00:58:12.866Z[UTC]",
    "searchQuery" : "charlest",
    "searchInteractionURIs" : [
    ]
  },
  {
    "platform" : "IPHONE",
    "searchTime" : "2023-08-26T00:58:13.270Z[UTC]",
    "searchQuery" : "charlest",
    "searchInteractionURIs" : [
      "spotify:track:3R6yNicsZrWF8ybl02imcB"
    ]
  },
  {
    "platform" : "IPHONE",
    "searchTime" : "2023-08-26T01:23:52.684Z[UTC]",
    "searchQuery" : "utop",
    "searchInteractionURIs" : [
      "spotify:album:18NOKLkZETa4sWwLMIm0UZ"
    ]
  },
  {
    "platform" : "IPHONE",
    "searchTime" : "2023-08-26T01:30:33.898Z[UTC]",
    "searchQuery" : "ok c",
    "searchInteractionURIs" : [
      "spotify:album:0tzfI6NFJqcJkWb23R3lRZ"
    ]
  },
  {
    "platform" : "IPHONE",
    "searchTime" : "2023-08-26T02:24:45.874Z[UTC]",
    "searchQuery" : "12",
    "searchInteractionURIs" : [
      "spotify:track:6Yu1OL8I0D4vjOzYdsXYGK"
    ]
  },
  {
    "platform" : "IPHONE_ARM64",
    "searchTime" : "2023-08-26T02:38:31.527Z[UTC]",
    "searchQuery" : "tgese",
    "searchInteractionURIs" : [
    ]
  },
  {
    "platform" : "IPHONE",
    "searchTime" : "2023-08-26T02:38:32.915Z[UTC]",
    "searchQuery" : "tgese guy",
    "searchInteractionURIs" : [
      "spotify:show:0DCF4F4r78p0eXiD3fyh2L"
    ]
  },
  {
    "platform" : "IPHONE",
    "searchTime" : "2023-08-26T03:03:45.296Z[UTC]",
    "searchQuery" : "angl",
    "searchInteractionURIs" : [
      "spotify:album:6Jx4cGhWHewTcfKDJKguBQ"
    ]
  },
  {
    "platform" : "IPHONE_ARM64",
    "searchTime" : "2023-08-26T03:56:21.868Z[UTC]",
    "searchQuery" : "r",
    "searchInteractionURIs" : [
    ]
  },
  {
    "platform" : "IPHONE_ARM64",
    "searchTime" : "2023-08-26T03:56:22.188Z[UTC]",
    "searchQuery" : "ro",
    "searchInteractionURIs" : [
    ]
  },
  {
    "platform" : "IPHONE",
    "searchTime" : "2023-08-26T03:56:22.825Z[UTC]",
    "searchQuery" : "room",
    "searchInteractionURIs" : [
      "spotify:album:3HFbH1loOUbqCyPsLuHLLh"
    ]
  },
  {
    "platform" : "IPHONE",
    "searchTime" : "2023-08-27T18:23:36.265Z[UTC]",
    "searchQuery" : "cig",
    "searchInteractionURIs" : [
      "spotify:playlist:4oSLOBQVHNFItpEhKeVbPC"
    ]
  },
  {
    "platform" : "IPHONE",
    "searchTime" : "2023-08-27T18:47:16.072Z[UTC]",
    "searchQuery" : "12",
    "searchInteractionURIs" : [
      "spotify:track:6Yu1OL8I0D4vjOzYdsXYGK"
    ]
  },
  {
    "platform" : "IPHONE_ARM64",
    "searchTime" : "2023-08-27T19:09:54.704Z[UTC]",
    "searchQuery" : "bing",
    "searchInteractionURIs" : [
    ]
  },
  {
    "platform" : "IPHONE",
    "searchTime" : "2023-08-27T19:09:55.485Z[UTC]",
    "searchQuery" : "binge ea",
    "searchInteractionURIs" : [
      "spotify:show:5PyvKiMZ873NtIJrvrTslR",
      "spotify:show:6LUcZST0B3x2lT89tsDNQY",
      "spotify:episode:3nz2AjpLAEmk3fbe8XvREk",
      "spotify:episode:46Mwt3g41qOUB5N8exJ3C0"
    ]
  },
  {
    "platform" : "IPHONE",
    "searchTime" : "2023-08-27T19:11:56.267Z[UTC]",
    "searchQuery" : "stick",
    "searchInteractionURIs" : [
      "spotify:track:0GNVXNz7Jkicfk2mp5OyG5"
    ]
  },
  {
    "platform" : "IPHONE_ARM64",
    "searchTime" : "2023-08-27T19:19:37.755Z[UTC]",
    "searchQuery" : "hai",
    "searchInteractionURIs" : [
    ]
  },
  {
    "platform" : "IPHONE",
    "searchTime" : "2023-08-27T19:19:38.109Z[UTC]",
    "searchQuery" : "hail",
    "searchInteractionURIs" : [
      "spotify:album:5mzoI3VH0ZWk1pLFR6RoYy",
      "spotify:album:5mzoI3VH0ZWk1pLFR6RoYy"
    ]
  },
  {
    "platform" : "IPHONE",
    "searchTime" : "2023-08-27T20:52:45.798Z[UTC]",
    "searchQuery" : "these guy",
    "searchInteractionURIs" : [
      "spotify:show:0DCF4F4r78p0eXiD3fyh2L"
    ]
  },
  {
    "platform" : "IPHONE",
    "searchTime" : "2023-08-27T21:48:48.513Z[UTC]",
    "searchQuery" : "analyt",
    "searchInteractionURIs" : [
      "spotify:show:2ReJKUbDtcom5U0GgpOlAz"
    ]
  },
  {
    "platform" : "IPHONE_ARM64",
    "searchTime" : "2023-08-28T15:54:29.840Z[UTC]",
    "searchQuery" : "let fo",
    "searchInteractionURIs" : [
    ]
  },
  {
    "platform" : "IPHONE_ARM64",
    "searchTime" : "2023-08-28T15:54:58.495Z[UTC]",
    "searchQuery" : "12",
    "searchInteractionURIs" : [
    ]
  },
  {
    "platform" : "IPHONE",
    "searchTime" : "2023-08-28T16:00:32.283Z[UTC]",
    "searchQuery" : "travis",
    "searchInteractionURIs" : [
      "spotify:artist:0Y5tJX1MQlPlqiwlOH1tJY"
    ]
  },
  {
    "platform" : "IPHONE_ARM64",
    "searchTime" : "2023-08-28T16:01:24.670Z[UTC]",
    "searchQuery" : "ri",
    "searchInteractionURIs" : [
    ]
  },
  {
    "platform" : "IPHONE_ARM64",
    "searchTime" : "2023-08-28T16:01:25.909Z[UTC]",
    "searchQuery" : "river of ",
    "searchInteractionURIs" : [
    ]
  },
  {
    "platform" : "IPHONE_ARM64",
    "searchTime" : "2023-08-28T16:01:26.048Z[UTC]",
    "searchQuery" : "river of br",
    "searchInteractionURIs" : [
    ]
  },
  {
    "platform" : "IPHONE",
    "searchTime" : "2023-08-28T16:01:26.715Z[UTC]",
    "searchQuery" : "river of brake",
    "searchInteractionURIs" : [
      "spotify:track:6ETWn02Bv8JIYXHvSoQD5u",
      "spotify:track:6ETWn02Bv8JIYXHvSoQD5u"
    ]
  },
  {
    "platform" : "IPHONE",
    "searchTime" : "2023-08-28T16:01:39.572Z[UTC]",
    "searchQuery" : "instant",
    "searchInteractionURIs" : [
      "spotify:track:2cGxRwrMyEAp8dEbuZaVv6"
    ]
  },
  {
    "platform" : "IPHONE_ARM64",
    "searchTime" : "2023-08-28T16:01:48.465Z[UTC]",
    "searchQuery" : "just l",
    "searchInteractionURIs" : [
    ]
  },
  {
    "platform" : "IPHONE",
    "searchTime" : "2023-08-28T16:01:49.437Z[UTC]",
    "searchQuery" : "just lime he",
    "searchInteractionURIs" : [
      "spotify:track:76GlO5H5RT6g7y0gev86Nk",
      "spotify:track:1KSkVwl54ghzE1jSbsVNBr"
    ]
  },
  {
    "platform" : "IPHONE_ARM64",
    "searchTime" : "2023-08-28T16:01:59.080Z[UTC]",
    "searchQuery" : "my ",
    "searchInteractionURIs" : [
    ]
  },
  {
    "platform" : "IPHONE_ARM64",
    "searchTime" : "2023-08-28T16:01:59.264Z[UTC]",
    "searchQuery" : "my c",
    "searchInteractionURIs" : [
    ]
  },
  {
    "platform" : "IPHONE",
    "searchTime" : "2023-08-28T16:01:59.631Z[UTC]",
    "searchQuery" : "my chem",
    "searchInteractionURIs" : [
      "spotify:artist:7FBcuc1gsnv6Y1nwFtNRCb"
    ]
  },
  {
    "platform" : "IPHONE_ARM64",
    "searchTime" : "2023-08-28T16:02:38.554Z[UTC]",
    "searchQuery" : "sp",
    "searchInteractionURIs" : [
    ]
  },
  {
    "platform" : "IPHONE_ARM64",
    "searchTime" : "2023-08-28T16:02:39.053Z[UTC]",
    "searchQuery" : "space ",
    "searchInteractionURIs" : [
    ]
  },
  {
    "platform" : "IPHONE",
    "searchTime" : "2023-08-28T16:02:39.697Z[UTC]",
    "searchQuery" : "space song",
    "searchInteractionURIs" : [
      "spotify:track:7H0ya83CMmgFcOhw0UB6ow"
    ]
  },
  {
    "platform" : "IPHONE_ARM64",
    "searchTime" : "2023-08-28T16:02:48.927Z[UTC]",
    "searchQuery" : "the wnd of ",
    "searchInteractionURIs" : [
    ]
  },
  {
    "platform" : "IPHONE",
    "searchTime" : "2023-08-28T16:02:50.108Z[UTC]",
    "searchQuery" : "the wnd of the ",
    "searchInteractionURIs" : [
      "spotify:track:5DTOOkooKFUvWj1XQTFa09",
      "spotify:track:5DTOOkooKFUvWj1XQTFa09"
    ]
  },
  {
    "platform" : "IPHONE",
    "searchTime" : "2023-08-28T23:30:16.568Z[UTC]",
    "searchQuery" : "sunset ",
    "searchInteractionURIs" : [
      "spotify:track:203bhpOhWluOytYjvwQfl7"
    ]
  },
  {
    "platform" : "",
    "searchTime" : "2023-08-29T00:16:30.371Z[UTC]",
    "searchQuery" : "🇧🇷",
    "searchInteractionURIs" : [
    ]
  },
  {
    "platform" : "",
    "searchTime" : "2023-08-29T00:16:30.481Z[UTC]",
    "searchQuery" : "🇧🇷",
    "searchInteractionURIs" : [
    ]
  },
  {
    "platform" : "",
    "searchTime" : "2023-08-29T00:16:34.213Z[UTC]",
    "searchQuery" : "5",
    "searchInteractionURIs" : [
    ]
  },
  {
    "platform" : "",
    "searchTime" : "2023-08-29T00:16:34.275Z[UTC]",
    "searchQuery" : "5",
    "searchInteractionURIs" : [
    ]
  },
  {
    "platform" : "",
    "searchTime" : "2023-08-29T00:16:34.483Z[UTC]",
    "searchQuery" : "50",
    "searchInteractionURIs" : [
    ]
  },
  {
    "platform" : "",
    "searchTime" : "2023-08-29T00:16:34.541Z[UTC]",
    "searchQuery" : "50",
    "searchInteractionURIs" : [
    ]
  },
  {
    "platform" : "",
    "searchTime" : "2023-08-29T00:16:34.590Z[UTC]",
    "searchQuery" : "505",
    "searchInteractionURIs" : [
    ]
  },
  {
    "platform" : "IPHONE",
    "searchTime" : "2023-08-29T00:16:34.834Z[UTC]",
    "searchQuery" : "505",
    "searchInteractionURIs" : [
      "spotify:track:58ge6dfP91o9oXMzq3XkIS"
    ]
  },
  {
    "platform" : "IPHONE",
    "searchTime" : "2023-08-30T23:06:51.110Z[UTC]",
    "searchQuery" : "river of",
    "searchInteractionURIs" : [
      "spotify:track:6ETWn02Bv8JIYXHvSoQD5u"
    ]
  },
  {
    "platform" : "IPHONE",
    "searchTime" : "2023-08-31T16:50:28.153Z[UTC]",
    "searchQuery" : "let",
    "searchInteractionURIs" : [
      "spotify:track:1CeC8kOYxUTCC2wHGtWROD"
    ]
  },
  {
    "platform" : "IPHONE",
    "searchTime" : "2023-09-01T01:05:41.155Z[UTC]",
    "searchQuery" : "kace",
    "searchInteractionURIs" : [
    ]
  },
  {
    "platform" : "IPHONE_ARM64",
    "searchTime" : "2023-09-01T01:06:00.220Z[UTC]",
    "searchQuery" : "a",
    "searchInteractionURIs" : [
    ]
  },
  {
    "platform" : "IPHONE",
    "searchTime" : "2023-09-01T01:06:01.366Z[UTC]",
    "searchQuery" : "august",
    "searchInteractionURIs" : [
      "spotify:track:3hUxzQpSfdDqwM3ZTFQY0K"
    ]
  },
  {
    "platform" : "IPHONE",
    "searchTime" : "2023-09-01T01:12:16.893Z[UTC]",
    "searchQuery" : "12:51",
    "searchInteractionURIs" : [
      "spotify:track:6Yu1OL8I0D4vjOzYdsXYGK"
    ]
  },
  {
    "platform" : "IPHONE_ARM64",
    "searchTime" : "2023-09-01T01:12:23.171Z[UTC]",
    "searchQuery" : "let ",
    "searchInteractionURIs" : [
    ]
  },
  {
    "platform" : "IPHONE",
    "searchTime" : "2023-09-01T01:12:23.870Z[UTC]",
    "searchQuery" : "let dow",
    "searchInteractionURIs" : [
      "spotify:track:1CeC8kOYxUTCC2wHGtWROD"
    ]
  },
  {
    "platform" : "IPHONE_ARM64",
    "searchTime" : "2023-09-01T01:30:10.599Z[UTC]",
    "searchQuery" : "cough ",
    "searchInteractionURIs" : [
    ]
  },
  {
    "platform" : "IPHONE_ARM64",
    "searchTime" : "2023-09-01T01:30:11.156Z[UTC]",
    "searchQuery" : "cough s",
    "searchInteractionURIs" : [
    ]
  },
  {
    "platform" : "IPHONE",
    "searchTime" : "2023-09-01T01:30:11.804Z[UTC]",
    "searchQuery" : "cough syr",
    "searchInteractionURIs" : [
      "spotify:track:1oLMC3cBot39A4Kv4tHFf9",
      "spotify:track:1oLMC3cBot39A4Kv4tHFf9"
    ]
  },
  {
    "platform" : "IPHONE_ARM64",
    "searchTime" : "2023-09-01T01:30:31.559Z[UTC]",
    "searchQuery" : "198",
    "searchInteractionURIs" : [
    ]
  },
  {
    "platform" : "IPHONE_ARM64",
    "searchTime" : "2023-09-01T01:30:32.008Z[UTC]",
    "searchQuery" : "1980",
    "searchInteractionURIs" : [
    ]
  },
  {
    "platform" : "IPHONE",
    "searchTime" : "2023-09-01T01:30:32.774Z[UTC]",
    "searchQuery" : "1980s",
    "searchInteractionURIs" : [
      "spotify:track:3VzULnaqPKf1deQyZ5W4Ah"
    ]
  },
  {
    "platform" : "IPHONE",
    "searchTime" : "2023-09-01T01:30:40.598Z[UTC]",
    "searchQuery" : "angel",
    "searchInteractionURIs" : [
      "spotify:track:2m6Ko3CY1qXNNja8AlugNc"
    ]
  },
  {
    "platform" : "IPHONE_ARM64",
    "searchTime" : "2023-09-01T01:54:12.008Z[UTC]",
    "searchQuery" : "look wh",
    "searchInteractionURIs" : [
    ]
  },
  {
    "platform" : "IPHONE",
    "searchTime" : "2023-09-01T01:54:13.050Z[UTC]",
    "searchQuery" : "look what you",
    "searchInteractionURIs" : [
      "spotify:track:1P17dC1amhFzptugyAO7Il"
    ]
  },
  {
    "platform" : "IPHONE",
    "searchTime" : "2023-09-01T02:11:34.357Z[UTC]",
    "searchQuery" : "ok com",
    "searchInteractionURIs" : [
      "spotify:album:6dVIqQ8qmQ5GBnJ9shOYGE"
    ]
  },
  {
    "platform" : "IPHONE",
    "searchTime" : "2023-09-01T04:55:22.345Z[UTC]",
    "searchQuery" : "carti",
    "searchInteractionURIs" : [
      "spotify:artist:699OTQXzgjhIYAHMy9RyPD"
    ]
  },
  {
    "platform" : "IPHONE",
    "searchTime" : "2023-09-01T15:20:49.938Z[UTC]",
    "searchQuery" : "slow",
    "searchInteractionURIs" : [
      "spotify:artist:72X6FHxaShda0XeQw3vbeF"
    ]
  },
  {
    "platform" : "IPHONE_ARM64",
    "searchTime" : "2023-09-01T22:12:45.830Z[UTC]",
    "searchQuery" : "zac",
    "searchInteractionURIs" : [
    ]
  },
  {
    "platform" : "IPHONE",
    "searchTime" : "2023-09-01T22:12:46.363Z[UTC]",
    "searchQuery" : "zach ",
    "searchInteractionURIs" : [
      "spotify:album:6PbnGueEO6LGodPfvNldYf"
    ]
  },
  {
    "platform" : "IPHONE_ARM64",
    "searchTime" : "2023-09-01T22:44:32.902Z[UTC]",
    "searchQuery" : "just like",
    "searchInteractionURIs" : [
    ]
  },
  {
    "platform" : "IPHONE",
    "searchTime" : "2023-09-01T22:44:33.245Z[UTC]",
    "searchQuery" : "just like ",
    "searchInteractionURIs" : [
      "spotify:track:76GlO5H5RT6g7y0gev86Nk"
    ]
  },
  {
    "platform" : "IPHONE",
    "searchTime" : "2023-09-02T15:30:51.642Z[UTC]",
    "searchQuery" : "califo",
    "searchInteractionURIs" : [
      "spotify:track:7oTE1KmtU2ml9zBhv9Reao"
    ]
  },
  {
    "platform" : "IPHONE",
    "searchTime" : "2023-09-02T23:03:36.151Z[UTC]",
    "searchQuery" : "cig",
    "searchInteractionURIs" : [
      "spotify:playlist:4oSLOBQVHNFItpEhKeVbPC"
    ]
  },
  {
    "platform" : "IPHONE_ARM64",
    "searchTime" : "2023-09-02T23:03:49.654Z[UTC]",
    "searchQuery" : "cigar",
    "searchInteractionURIs" : [
    ]
  },
  {
    "platform" : "IPHONE_ARM64",
    "searchTime" : "2023-09-02T23:03:52.262Z[UTC]",
    "searchQuery" : "cigarett",
    "searchInteractionURIs" : [
    ]
  },
  {
    "platform" : "IPHONE_ARM64",
    "searchTime" : "2023-09-02T23:03:53.109Z[UTC]",
    "searchQuery" : "cigarettes af",
    "searchInteractionURIs" : [
    ]
  },
  {
    "platform" : "IPHONE_ARM64",
    "searchTime" : "2023-09-02T23:03:53.231Z[UTC]",
    "searchQuery" : "cigarettes aft",
    "searchInteractionURIs" : [
    ]
  },
  {
    "platform" : "IPHONE",
    "searchTime" : "2023-09-02T23:03:55.877Z[UTC]",
    "searchQuery" : "cigarettes after sex setlo",
    "searchInteractionURIs" : [
      "spotify:playlist:2GQaKjIVenHODzB3igZdzj",
      "spotify:playlist:4oSLOBQVHNFItpEhKeVbPC"
    ]
  },
  {
    "platform" : "IPHONE",
    "searchTime" : "2023-09-03T15:57:28.097Z[UTC]",
    "searchQuery" : "hard ",
    "searchInteractionURIs" : [
      "spotify:track:0OM9ri37LIbPc9hffwsyb1"
    ]
  },
  {
    "platform" : "IPHONE",
    "searchTime" : "2023-09-05T01:06:15.046Z[UTC]",
    "searchQuery" : "how to nav",
    "searchInteractionURIs" : [
    ]
  },
  {
    "platform" : "IPHONE_ARM64",
    "searchTime" : "2023-09-05T01:06:41.741Z[UTC]",
    "searchQuery" : "how to navigat",
    "searchInteractionURIs" : [
    ]
  },
  {
    "platform" : "IPHONE_ARM64",
    "searchTime" : "2023-09-05T01:06:55.592Z[UTC]",
    "searchQuery" : "how to navigate your 20s",
    "searchInteractionURIs" : [
    ]
  },
  {
    "platform" : "IPHONE_ARM64",
    "searchTime" : "2023-09-05T01:07:07.389Z[UTC]",
    "searchQuery" : "navigating",
    "searchInteractionURIs" : [
    ]
  },
  {
    "platform" : "IPHONE",
    "searchTime" : "2023-09-05T01:07:07.632Z[UTC]",
    "searchQuery" : "navigating ",
    "searchInteractionURIs" : [
      "spotify:search:navigating+your+20s"
    ]
  },
  {
    "platform" : "IPHONE",
    "searchTime" : "2023-09-05T01:07:10.134Z[UTC]",
    "searchQuery" : "navigating your 20s",
    "searchInteractionURIs" : [
      "spotify:show:52U076RD6ux05ylY9Ajjlt"
    ]
  },
  {
    "platform" : "IPHONE_ARM64",
    "searchTime" : "2023-09-05T01:09:35.271Z[UTC]",
    "searchQuery" : "c",
    "searchInteractionURIs" : [
    ]
  },
  {
    "platform" : "IPHONE",
    "searchTime" : "2023-09-05T01:09:35.870Z[UTC]",
    "searchQuery" : "crush",
    "searchInteractionURIs" : [
      "spotify:track:78sdhV2qA9aFFzwhPdEQh5"
    ]
  },
  {
    "platform" : "IPHONE_ARM64",
    "searchTime" : "2023-09-05T22:02:31.869Z[UTC]",
    "searchQuery" : " sun b",
    "searchInteractionURIs" : [
    ]
  },
  {
    "platform" : "IPHONE",
    "searchTime" : "2023-09-05T22:02:32.103Z[UTC]",
    "searchQuery" : " sun ",
    "searchInteractionURIs" : [
      "spotify:track:6fKIyDJHZ9m84jRhSmpuwS"
    ]
  },
  {
    "platform" : "IPHONE_ARM64",
    "searchTime" : "2023-09-07T01:36:01.651Z[UTC]",
    "searchQuery" : "r",
    "searchInteractionURIs" : [
    ]
  },
  {
    "platform" : "IPHONE",
    "searchTime" : "2023-09-07T01:36:02.715Z[UTC]",
    "searchQuery" : "room",
    "searchInteractionURIs" : [
      "spotify:album:3HFbH1loOUbqCyPsLuHLLh"
    ]
  },
  {
    "platform" : "IPHONE",
    "searchTime" : "2023-09-08T01:56:59.024Z[UTC]",
    "searchQuery" : "am",
    "searchInteractionURIs" : [
      "spotify:track:4ltqfN12ohaVZdM6C45gMg"
    ]
  },
  {
    "platform" : "IPHONE_ARM64",
    "searchTime" : "2023-09-08T15:46:40.938Z[UTC]",
    "searchQuery" : "g",
    "searchInteractionURIs" : [
    ]
  },
  {
    "platform" : "IPHONE",
    "searchTime" : "2023-09-08T15:46:41.218Z[UTC]",
    "searchQuery" : "guts",
    "searchInteractionURIs" : [
      "spotify:artist:1McMsnEElThX1knmY4oliG"
    ]
  },
  {
    "platform" : "IPHONE_ARM64",
    "searchTime" : "2023-09-09T02:24:05.437Z[UTC]",
    "searchQuery" : "ri",
    "searchInteractionURIs" : [
    ]
  },
  {
    "platform" : "IPHONE_ARM64",
    "searchTime" : "2023-09-09T02:24:05.742Z[UTC]",
    "searchQuery" : "rich ",
    "searchInteractionURIs" : [
    ]
  },
  {
    "platform" : "IPHONE",
    "searchTime" : "2023-09-09T02:24:06.415Z[UTC]",
    "searchQuery" : "rich men",
    "searchInteractionURIs" : [
      "spotify:track:78Du4CMFgnhdlG33gblkiP"
    ]
  },
  {
    "platform" : "IPHONE_ARM64",
    "searchTime" : "2023-09-09T02:28:42.094Z[UTC]",
    "searchQuery" : "thi",
    "searchInteractionURIs" : [
    ]
  },
  {
    "platform" : "IPHONE",
    "searchTime" : "2023-09-09T02:28:42.486Z[UTC]",
    "searchQuery" : "this ",
    "searchInteractionURIs" : [
      "spotify:track:7kt9e9LFSpN1zQtYEl19o1"
    ]
  },
  {
    "platform" : "IPHONE_ARM64",
    "searchTime" : "2023-09-09T17:41:38.022Z[UTC]",
    "searchQuery" : "la",
    "searchInteractionURIs" : [
    ]
  },
  {
    "platform" : "IPHONE",
    "searchTime" : "2023-09-09T17:41:38.780Z[UTC]",
    "searchQuery" : "laugh it",
    "searchInteractionURIs" : [
      "spotify:track:1UdagWdhnDqK9a0aWQpReY"
    ]
  },
  {
    "platform" : "IPHONE_ARM64",
    "searchTime" : "2023-09-09T18:24:40.607Z[UTC]",
    "searchQuery" : "125",
    "searchInteractionURIs" : [
    ]
  },
  {
    "platform" : "IPHONE",
    "searchTime" : "2023-09-09T18:24:40.769Z[UTC]",
    "searchQuery" : "1251",
    "searchInteractionURIs" : [
      "spotify:track:6Yu1OL8I0D4vjOzYdsXYGK"
    ]
  },
  {
    "platform" : "IPHONE",
    "searchTime" : "2023-09-09T20:39:40.519Z[UTC]",
    "searchQuery" : "amnesi",
    "searchInteractionURIs" : [
      "spotify:album:1HrMmB5useeZ0F5lHrMvl0"
    ]
  },
  {
    "platform" : "IPHONE_ARM64",
    "searchTime" : "2023-09-11T21:59:36.296Z[UTC]",
    "searchQuery" : "i",
    "searchInteractionURIs" : [
    ]
  },
  {
    "platform" : "IPHONE_ARM64",
    "searchTime" : "2023-09-11T21:59:36.831Z[UTC]",
    "searchQuery" : "in u",
    "searchInteractionURIs" : [
    ]
  },
  {
    "platform" : "IPHONE",
    "searchTime" : "2023-09-11T21:59:37.105Z[UTC]",
    "searchQuery" : "in ut",
    "searchInteractionURIs" : [
      "spotify:album:7wOOA7l306K8HfBKfPoafr"
    ]
  },
  {
    "platform" : "",
    "searchTime" : "2023-09-12T00:40:25.730Z[UTC]",
    "searchQuery" : "in ut",
    "searchInteractionURIs" : [
    ]
  },
  {
    "platform" : "IPHONE",
    "searchTime" : "2023-09-12T00:40:52.836Z[UTC]",
    "searchQuery" : "in ut",
    "searchInteractionURIs" : [
      "spotify:album:7wOOA7l306K8HfBKfPoafr"
    ]
  },
  {
    "platform" : "IPHONE",
    "searchTime" : "2023-09-12T22:26:05.064Z[UTC]",
    "searchQuery" : "fein",
    "searchInteractionURIs" : [
      "spotify:track:42VsgItocQwOQC3XWZ8JNA"
    ]
  },
  {
    "platform" : "IPHONE_ARM64",
    "searchTime" : "2023-09-13T03:39:00.741Z[UTC]",
    "searchQuery" : "fathe",
    "searchInteractionURIs" : [
    ]
  },
  {
    "platform" : "IPHONE",
    "searchTime" : "2023-09-13T03:39:01.143Z[UTC]",
    "searchQuery" : "father ",
    "searchInteractionURIs" : [
    ]
  },
  {
    "platform" : "IPHONE_ARM64",
    "searchTime" : "2023-09-13T15:44:47.253Z[UTC]",
    "searchQuery" : "ba",
    "searchInteractionURIs" : [
    ]
  },
  {
    "platform" : "IPHONE_ARM64",
    "searchTime" : "2023-09-13T15:44:47.705Z[UTC]",
    "searchQuery" : "backs",
    "searchInteractionURIs" : [
    ]
  },
  {
    "platform" : "IPHONE",
    "searchTime" : "2023-09-13T15:44:48Z[UTC]",
    "searchQuery" : "backse",
    "searchInteractionURIs" : [
      "spotify:artist:6p2HnfM955TI1bX34dkLnI"
    ]
  },
  {
    "platform" : "IPHONE",
    "searchTime" : "2023-09-13T21:43:48.629Z[UTC]",
    "searchQuery" : "carly",
    "searchInteractionURIs" : [
      "spotify:album:4bRYGKmKOkXvKL1QBf0cGk"
    ]
  },
  {
    "platform" : "IPHONE",
    "searchTime" : "2023-09-13T22:19:52.405Z[UTC]",
    "searchQuery" : "carly",
    "searchInteractionURIs" : [
    ]
  },
  {
    "platform" : "IPHONE",
    "searchTime" : "2023-09-14T01:48:10.753Z[UTC]",
    "searchQuery" : "cig",
    "searchInteractionURIs" : [
      "spotify:playlist:4oSLOBQVHNFItpEhKeVbPC"
    ]
  },
  {
    "platform" : "IPHONE",
    "searchTime" : "2023-09-14T04:01:23.546Z[UTC]",
    "searchQuery" : "fuck being sober",
    "searchInteractionURIs" : [
      "spotify:track:1aBCdCoHR7AwWQbiWEHdzA"
    ]
  },
  {
    "platform" : "IPHONE_ARM64",
    "searchTime" : "2023-09-14T21:17:12.767Z[UTC]",
    "searchQuery" : "emo",
    "searchInteractionURIs" : [
    ]
  },
  {
    "platform" : "IPHONE",
    "searchTime" : "2023-09-14T21:17:13.452Z[UTC]",
    "searchQuery" : "emotio",
    "searchInteractionURIs" : [
      "spotify:album:6UjZgFbK6CQptu8aOobzPV"
    ]
  },
  {
    "platform" : "IPHONE",
    "searchTime" : "2023-09-15T03:39:41.495Z[UTC]",
    "searchQuery" : "new ",
    "searchInteractionURIs" : [
      "spotify:playlist:37i9dQZF1DX4JAvHpjipBk"
    ]
  },
  {
    "platform" : "IPHONE_ARM64",
    "searchTime" : "2023-09-15T03:56:13.662Z[UTC]",
    "searchQuery" : "stro",
    "searchInteractionURIs" : [
    ]
  },
  {
    "platform" : "IPHONE",
    "searchTime" : "2023-09-15T03:56:14.250Z[UTC]",
    "searchQuery" : "strokes",
    "searchInteractionURIs" : [
      "spotify:artist:0epOFNiUfyON9EYx7Tpr6V",
      "spotify:album:3HFbH1loOUbqCyPsLuHLLh"
    ]
  },
  {
    "platform" : "IPHONE",
    "searchTime" : "2023-09-15T04:06:20.887Z[UTC]",
    "searchQuery" : "utop",
    "searchInteractionURIs" : [
      "spotify:album:18NOKLkZETa4sWwLMIm0UZ"
    ]
  },
  {
    "platform" : "IPHONE_ARM64",
    "searchTime" : "2023-09-15T04:08:32.195Z[UTC]",
    "searchQuery" : "dra",
    "searchInteractionURIs" : [
    ]
  },
  {
    "platform" : "IPHONE",
    "searchTime" : "2023-09-15T04:08:32.380Z[UTC]",
    "searchQuery" : "drake",
    "searchInteractionURIs" : [
      "spotify:artist:3TVXtAsR1Inumwj472S9r4"
    ]
  },
  {
    "platform" : "IPHONE_ARM64",
    "searchTime" : "2023-09-15T04:08:49.424Z[UTC]",
    "searchQuery" : "do",
    "searchInteractionURIs" : [
    ]
  },
  {
    "platform" : "IPHONE",
    "searchTime" : "2023-09-15T04:08:49.806Z[UTC]",
    "searchQuery" : "doja",
    "searchInteractionURIs" : [
      "spotify:artist:5cj0lLjcoR7YOSnhnX0Po5"
    ]
  },
  {
    "platform" : "IPHONE",
    "searchTime" : "2023-09-15T04:27:52.030Z[UTC]",
    "searchQuery" : "radio",
    "searchInteractionURIs" : [
      "spotify:artist:4Z8W4fKeB5YxbusRsdQVPb"
    ]
  },
  {
    "platform" : "IPHONE",
    "searchTime" : "2023-09-15T04:28:03.143Z[UTC]",
    "searchQuery" : "no si",
    "searchInteractionURIs" : [
    ]
  },
  {
    "platform" : "IPHONE",
    "searchTime" : "2023-09-15T18:02:22.388Z[UTC]",
    "searchQuery" : "born",
    "searchInteractionURIs" : [
      "spotify:artist:1KP6TWI40m7p3QBTU6u2xo"
    ]
  },
  {
    "platform" : "IPHONE_ARM64",
    "searchTime" : "2023-09-15T19:02:00.832Z[UTC]",
    "searchQuery" : "t",
    "searchInteractionURIs" : [
    ]
  },
  {
    "platform" : "IPHONE",
    "searchTime" : "2023-09-15T19:02:01.708Z[UTC]",
    "searchQuery" : "twohot",
    "searchInteractionURIs" : [
      "spotify:show:6kCMPmQxqL1gO0DNtqeyQl"
    ]
  },
  {
    "platform" : "IPHONE",
    "searchTime" : "2023-09-15T20:11:04.517Z[UTC]",
    "searchQuery" : "drake",
    "searchInteractionURIs" : [
      "spotify:artist:3TVXtAsR1Inumwj472S9r4"
    ]
  },
  {
    "platform" : "IPHONE_ARM64",
    "searchTime" : "2023-09-15T22:32:03.586Z[UTC]",
    "searchQuery" : "you ",
    "searchInteractionURIs" : [
    ]
  },
  {
    "platform" : "IPHONE",
    "searchTime" : "2023-09-15T22:32:04.260Z[UTC]",
    "searchQuery" : "you onl",
    "searchInteractionURIs" : [
      "spotify:track:4fPBB44eDH71YohayI4eKV"
    ]
  },
  {
    "platform" : "IPHONE_ARM64",
    "searchTime" : "2023-09-16T17:50:26.995Z[UTC]",
    "searchQuery" : "tge ",
    "searchInteractionURIs" : [
    ]
  },
  {
    "platform" : "IPHONE",
    "searchTime" : "2023-09-16T17:50:27.779Z[UTC]",
    "searchQuery" : "tge lon",
    "searchInteractionURIs" : [
      "spotify:album:3l2Gi0hMjZV2uvKoWlFkoQ"
    ]
  },
  {
    "platform" : "IPHONE_ARM64",
    "searchTime" : "2023-09-16T18:32:50.442Z[UTC]",
    "searchQuery" : "p",
    "searchInteractionURIs" : [
    ]
  },
  {
    "platform" : "IPHONE",
    "searchTime" : "2023-09-16T18:32:51.505Z[UTC]",
    "searchQuery" : "puthon",
    "searchInteractionURIs" : [
      "spotify:show:41Av6Rq81LfOT3Volz7W9D",
      "spotify:episode:3k3odcdIutNCmy6hH6zQkQ",
      "spotify:show:41Av6Rq81LfOT3Volz7W9D",
      "spotify:episode:3k3odcdIutNCmy6hH6zQkQ"
    ]
  },
  {
    "platform" : "IPHONE_ARM64",
    "searchTime" : "2023-09-17T15:48:40.169Z[UTC]",
    "searchQuery" : "sha",
    "searchInteractionURIs" : [
    ]
  },
  {
    "platform" : "IPHONE",
    "searchTime" : "2023-09-17T15:48:52.837Z[UTC]",
    "searchQuery" : "shane gillis",
    "searchInteractionURIs" : [
      "spotify:artist:4Voj5mMTNvEhyP1hmPJAeM"
    ]
  },
  {
    "platform" : "IPHONE",
    "searchTime" : "2023-09-17T16:15:20.607Z[UTC]",
    "searchQuery" : "cig",
    "searchInteractionURIs" : [
      "spotify:playlist:4oSLOBQVHNFItpEhKeVbPC"
    ]
  },
  {
    "platform" : "IPHONE",
    "searchTime" : "2023-09-17T20:33:05.283Z[UTC]",
    "searchQuery" : "12",
    "searchInteractionURIs" : [
      "spotify:track:6Yu1OL8I0D4vjOzYdsXYGK"
    ]
  },
  {
    "platform" : "IPHONE",
    "searchTime" : "2023-09-17T20:44:31.315Z[UTC]",
    "searchQuery" : "tele",
    "searchInteractionURIs" : [
      "spotify:track:1i9lZvlaDdWDPyXEE95aiq"
    ]
  },
  {
    "platform" : "IPHONE",
    "searchTime" : "2023-09-18T15:15:30.697Z[UTC]",
    "searchQuery" : "pisto",
    "searchInteractionURIs" : [
      "spotify:track:5g5XvfePSypMK6eiVL6BI7"
    ]
  },
  {
    "platform" : "IPHONE",
    "searchTime" : "2023-09-18T16:02:27.679Z[UTC]",
    "searchQuery" : "binch",
    "searchInteractionURIs" : [
      "spotify:show:5Uu04mHwFS9NeCeZ6v0r5U"
    ]
  },
  {
    "platform" : "IPHONE",
    "searchTime" : "2023-09-18T16:23:19.835Z[UTC]",
    "searchQuery" : "last pod",
    "searchInteractionURIs" : [
      "spotify:show:3yZg2MCkf31pPXiG4nznrg"
    ]
  },
  {
    "platform" : "IPHONE_ARM64",
    "searchTime" : "2023-09-18T22:01:38.634Z[UTC]",
    "searchQuery" : "an",
    "searchInteractionURIs" : [
    ]
  },
  {
    "platform" : "IPHONE",
    "searchTime" : "2023-09-18T22:01:39.284Z[UTC]",
    "searchQuery" : "analy",
    "searchInteractionURIs" : [
      "spotify:show:2ReJKUbDtcom5U0GgpOlAz"
    ]
  },
  {
    "platform" : "IPHONE_ARM64",
    "searchTime" : "2023-09-19T04:27:50.263Z[UTC]",
    "searchQuery" : "coc",
    "searchInteractionURIs" : [
    ]
  },
  {
    "platform" : "IPHONE",
    "searchTime" : "2023-09-19T04:27:50.742Z[UTC]",
    "searchQuery" : "cocte",
    "searchInteractionURIs" : [
      "spotify:album:5lEphbceIgaK1XxWeSrC9E"
    ]
  },
  {
    "platform" : "IPHONE_ARM64",
    "searchTime" : "2023-09-20T02:59:22.297Z[UTC]",
    "searchQuery" : "lana al-khati",
    "searchInteractionURIs" : [
    ]
  },
  {
    "platform" : "IPHONE",
    "searchTime" : "2023-09-20T02:59:22.586Z[UTC]",
    "searchQuery" : "lana al-khatib",
    "searchInteractionURIs" : [
      "spotify:user:lanaalk_"
    ]
  },
  {
    "platform" : "IPHONE_ARM64",
    "searchTime" : "2023-09-20T02:59:38.464Z[UTC]",
    "searchQuery" : "nadeen",
    "searchInteractionURIs" : [
    ]
  },
  {
    "platform" : "IPHONE",
    "searchTime" : "2023-09-20T04:43:45.057Z[UTC]",
    "searchQuery" : "aph",
    "searchInteractionURIs" : [
      "spotify:artist:6kBDZFXuLrZgHnvmPu9NsG"
    ]
  },
  {
    "platform" : "IPHONE",
    "searchTime" : "2023-09-20T04:47:15.685Z[UTC]",
    "searchQuery" : "radio",
    "searchInteractionURIs" : [
      "spotify:artist:4Z8W4fKeB5YxbusRsdQVPb"
    ]
  },
  {
    "platform" : "IPHONE",
    "searchTime" : "2023-09-20T14:15:52.329Z[UTC]",
    "searchQuery" : "eliza mc",
    "searchInteractionURIs" : [
      "spotify:artist:5jy9tglmQRLmTmcqz2qyUa"
    ]
  },
  {
    "platform" : "IPHONE",
    "searchTime" : "2023-09-20T16:35:44.283Z[UTC]",
    "searchQuery" : "drake",
    "searchInteractionURIs" : [
      "spotify:artist:3TVXtAsR1Inumwj472S9r4"
    ]
  },
  {
    "platform" : "IPHONE",
    "searchTime" : "2023-09-20T17:05:51.462Z[UTC]",
    "searchQuery" : "weird",
    "searchInteractionURIs" : [
      "spotify:track:4wajJ1o7jWIg62YqpkHC7S"
    ]
  },
  {
    "platform" : "IPHONE",
    "searchTime" : "2023-09-20T17:18:29.407Z[UTC]",
    "searchQuery" : "amer",
    "searchInteractionURIs" : [
      "spotify:track:4ltqfN12ohaVZdM6C45gMg",
      "spotify:show:41zWZdWCpVQrKj7ykQnXRc"
    ]
  },
  {
    "platform" : "IPHONE",
    "searchTime" : "2023-09-21T03:40:58.488Z[UTC]",
    "searchQuery" : "very ",
    "searchInteractionURIs" : [
      "spotify:track:0hUit24g1EIoATdKYWUiRj"
    ]
  },
  {
    "platform" : "IPHONE_ARM64",
    "searchTime" : "2023-09-21T03:43:26.700Z[UTC]",
    "searchQuery" : "afte",
    "searchInteractionURIs" : [
    ]
  },
  {
    "platform" : "IPHONE",
    "searchTime" : "2023-09-21T03:43:26.868Z[UTC]",
    "searchQuery" : "after",
    "searchInteractionURIs" : [
      "spotify:album:4yP0hdKOZPNshxUOjY0cZj"
    ]
  },
  {
    "platform" : "IPHONE_ARM64",
    "searchTime" : "2023-09-21T04:22:38.029Z[UTC]",
    "searchQuery" : "jersey",
    "searchInteractionURIs" : [
    ]
  },
  {
    "platform" : "IPHONE",
    "searchTime" : "2023-09-21T04:22:38.571Z[UTC]",
    "searchQuery" : "jersey gi",
    "searchInteractionURIs" : [
      "spotify:search:jersey+giant+tyler+childers"
    ]
  },
  {
    "platform" : "IPHONE",
    "searchTime" : "2023-09-21T04:22:41.765Z[UTC]",
    "searchQuery" : "jersey giant tyler childers",
    "searchInteractionURIs" : [
      "spotify:track:3hEkAosl2ZuO9FltxY5L1R",
      "spotify:episode:6pp6sC9ue254pNyS7Dtinz",
      "spotify:artist:13ZEDW6vyBF12HYcZRr4EV"
    ]
  },
  {
    "platform" : "IPHONE_ARM64",
    "searchTime" : "2023-09-21T16:54:54.162Z[UTC]",
    "searchQuery" : "grad",
    "searchInteractionURIs" : [
    ]
  },
  {
    "platform" : "IPHONE",
    "searchTime" : "2023-09-21T16:54:54.388Z[UTC]",
    "searchQuery" : "gradu",
    "searchInteractionURIs" : [
      "spotify:album:4SZko61aMnmgvNhfhgTuD3"
    ]
  },
  {
    "platform" : "IPHONE",
    "searchTime" : "2023-09-22T03:56:30.671Z[UTC]",
    "searchQuery" : "norman",
    "searchInteractionURIs" : [
      "spotify:album:5XpEKORZ4y6OrCZSKsi46A"
    ]
  },
  {
    "platform" : "IPHONE",
    "searchTime" : "2023-09-22T04:04:20.795Z[UTC]",
    "searchQuery" : "ethe",
    "searchInteractionURIs" : [
      "spotify:artist:0avMDS4HyoCEP6RqZJWpY2"
    ]
  },
  {
    "platform" : "IPHONE_ARM64",
    "searchTime" : "2023-09-22T17:26:38.059Z[UTC]",
    "searchQuery" : "stroke",
    "searchInteractionURIs" : [
    ]
  },
  {
    "platform" : "IPHONE",
    "searchTime" : "2023-09-22T17:26:38.229Z[UTC]",
    "searchQuery" : "strokes",
    "searchInteractionURIs" : [
      "spotify:playlist:37i9dQZF1E4sGDGKZyZIri"
    ]
  },
  {
    "platform" : "IPHONE_ARM64",
    "searchTime" : "2023-09-22T19:19:39.623Z[UTC]",
    "searchQuery" : "my",
    "searchInteractionURIs" : [
    ]
  },
  {
    "platform" : "IPHONE_ARM64",
    "searchTime" : "2023-09-22T19:19:39.707Z[UTC]",
    "searchQuery" : "my blo",
    "searchInteractionURIs" : [
    ]
  },
  {
    "platform" : "IPHONE",
    "searchTime" : "2023-09-22T19:19:40.009Z[UTC]",
    "searchQuery" : "my bloody",
    "searchInteractionURIs" : [
      "spotify:album:3GH4IiI6jQAIvnHVdb5FB6"
    ]
  },
  {
    "platform" : "IPHONE_ARM64",
    "searchTime" : "2023-09-22T19:25:52.959Z[UTC]",
    "searchQuery" : "this ",
    "searchInteractionURIs" : [
    ]
  },
  {
    "platform" : "IPHONE",
    "searchTime" : "2023-09-22T19:25:53.388Z[UTC]",
    "searchQuery" : "this am",
    "searchInteractionURIs" : [
      "spotify:show:41zWZdWCpVQrKj7ykQnXRc"
    ]
  },
  {
    "platform" : "IPHONE_ARM64",
    "searchTime" : "2023-09-22T19:42:57.958Z[UTC]",
    "searchQuery" : "this am",
    "searchInteractionURIs" : [
    ]
  },
  {
    "platform" : "IPHONE",
    "searchTime" : "2023-09-22T20:23:58.054Z[UTC]",
    "searchQuery" : "the be ds",
    "searchInteractionURIs" : [
      "spotify:album:35UJLpClj5EDrhpNIi4DFg"
    ]
  },
  {
    "platform" : "IPHONE_ARM64",
    "searchTime" : "2023-09-23T18:01:11.390Z[UTC]",
    "searchQuery" : "mi",
    "searchInteractionURIs" : [
    ]
  },
  {
    "platform" : "IPHONE_ARM64",
    "searchTime" : "2023-09-23T18:01:11.727Z[UTC]",
    "searchQuery" : "mits",
    "searchInteractionURIs" : [
    ]
  },
  {
    "platform" : "IPHONE",
    "searchTime" : "2023-09-23T18:01:12.070Z[UTC]",
    "searchQuery" : "mitsk",
    "searchInteractionURIs" : [
      "spotify:album:2Cn1d2KgbkAqbZCJ1RzdkA"
    ]
  },
  {
    "platform" : "IPHONE",
    "searchTime" : "2023-09-25T14:45:53.952Z[UTC]",
    "searchQuery" : "the n",
    "searchInteractionURIs" : [
      "spotify:album:2xkZV2Hl1Omi8rk2D7t5lN"
    ]
  },
  {
    "platform" : "IPHONE",
    "searchTime" : "2023-09-25T15:34:38.808Z[UTC]",
    "searchQuery" : "lana",
    "searchInteractionURIs" : [
      "spotify:artist:00FQb4jTyendYWaN8pK0wa"
    ]
  },
  {
    "platform" : "IPHONE_ARM64",
    "searchTime" : "2023-09-25T16:06:08.702Z[UTC]",
    "searchQuery" : "h",
    "searchInteractionURIs" : [
    ]
  },
  {
    "platform" : "IPHONE",
    "searchTime" : "2023-09-25T16:06:09.704Z[UTC]",
    "searchQuery" : "huber",
    "searchInteractionURIs" : [
      "spotify:show:79CkJF3UJTHFV8Dse3Oy0P"
    ]
  },
  {
    "platform" : "IPHONE_ARM64",
    "searchTime" : "2023-09-26T02:12:19.738Z[UTC]",
    "searchQuery" : "HEL",
    "searchInteractionURIs" : [
    ]
  },
  {
    "platform" : "IPHONE_ARM64",
    "searchTime" : "2023-09-26T02:12:20.037Z[UTC]",
    "searchQuery" : "HELL",
    "searchInteractionURIs" : [
    ]
  },
  {
    "platform" : "IPHONE_ARM64",
    "searchTime" : "2023-09-26T02:12:20.442Z[UTC]",
    "searchQuery" : "HELLMOD",
    "searchInteractionURIs" : [
    ]
  },
  {
    "platform" : "IPHONE",
    "searchTime" : "2023-09-26T02:12:20.650Z[UTC]",
    "searchQuery" : "HELLMODE",
    "searchInteractionURIs" : [
      "spotify:album:7Gw4NIOgnylpbryrOJksn9"
    ]
  },
  {
    "platform" : "IPHONE_ARM64",
    "searchTime" : "2023-09-27T02:39:20.585Z[UTC]",
    "searchQuery" : "4",
    "searchInteractionURIs" : [
    ]
  },
  {
    "platform" : "IPHONE_ARM64",
    "searchTime" : "2023-09-27T15:26:23.393Z[UTC]",
    "searchQuery" : "runni",
    "searchInteractionURIs" : [
    ]
  },
  {
    "platform" : "",
    "searchTime" : "2023-09-30T00:41:58.878Z[UTC]",
    "searchQuery" : "l",
    "searchInteractionURIs" : [
    ]
  },
  {
    "platform" : "",
    "searchTime" : "2023-09-30T00:41:58.948Z[UTC]",
    "searchQuery" : "l",
    "searchInteractionURIs" : [
    ]
  },
  {
    "platform" : "",
    "searchTime" : "2023-09-30T00:41:59.087Z[UTC]",
    "searchQuery" : "li",
    "searchInteractionURIs" : [
    ]
  },
  {
    "platform" : "",
    "searchTime" : "2023-09-30T00:41:59.177Z[UTC]",
    "searchQuery" : "li",
    "searchInteractionURIs" : [
    ]
  },
  {
    "platform" : "",
    "searchTime" : "2023-09-30T00:41:59.245Z[UTC]",
    "searchQuery" : "lil",
    "searchInteractionURIs" : [
    ]
  },
  {
    "platform" : "",
    "searchTime" : "2023-09-30T00:41:59.331Z[UTC]",
    "searchQuery" : "lil",
    "searchInteractionURIs" : [
    ]
  },
  {
    "platform" : "",
    "searchTime" : "2023-09-30T00:41:59.435Z[UTC]",
    "searchQuery" : "lil ",
    "searchInteractionURIs" : [
    ]
  },
  {
    "platform" : "",
    "searchTime" : "2023-09-30T00:41:59.512Z[UTC]",
    "searchQuery" : "lil ",
    "searchInteractionURIs" : [
    ]
  },
  {
    "platform" : "",
    "searchTime" : "2023-09-30T00:41:59.720Z[UTC]",
    "searchQuery" : "lil i",
    "searchInteractionURIs" : [
    ]
  },
  {
    "platform" : "",
    "searchTime" : "2023-09-30T00:41:59.784Z[UTC]",
    "searchQuery" : "lil i",
    "searchInteractionURIs" : [
    ]
  },
  {
    "platform" : "IPHONE",
    "searchTime" : "2023-09-30T00:42:00.015Z[UTC]",
    "searchQuery" : "lil i",
    "searchInteractionURIs" : [
    ]
  },
  {
    "platform" : "",
    "searchTime" : "2023-09-30T00:42:00.364Z[UTC]",
    "searchQuery" : "lil ",
    "searchInteractionURIs" : [
    ]
  },
  {
    "platform" : "",
    "searchTime" : "2023-09-30T00:42:00.459Z[UTC]",
    "searchQuery" : "lil ",
    "searchInteractionURIs" : [
    ]
  },
  {
    "platform" : "IPHONE",
    "searchTime" : "2023-09-30T00:42:00.649Z[UTC]",
    "searchQuery" : "lil ",
    "searchInteractionURIs" : [
      "spotify:artist:4O15NlyKLIASxsJ0PrXPfz"
    ]
  },
  {
    "platform" : "",
    "searchTime" : "2023-09-30T00:44:24.549Z[UTC]",
    "searchQuery" : "g",
    "searchInteractionURIs" : [
    ]
  },
  {
    "platform" : "",
    "searchTime" : "2023-09-30T00:44:24.634Z[UTC]",
    "searchQuery" : "g",
    "searchInteractionURIs" : [
    ]
  },
  {
    "platform" : "",
    "searchTime" : "2023-09-30T00:44:24.802Z[UTC]",
    "searchQuery" : "go",
    "searchInteractionURIs" : [
    ]
  },
  {
    "platform" : "",
    "searchTime" : "2023-09-30T00:44:24.883Z[UTC]",
    "searchQuery" : "go",
    "searchInteractionURIs" : [
    ]
  },
  {
    "platform" : "",
    "searchTime" : "2023-09-30T00:44:25.041Z[UTC]",
    "searchQuery" : "goo",
    "searchInteractionURIs" : [
    ]
  },
  {
    "platform" : "",
    "searchTime" : "2023-09-30T00:44:25.104Z[UTC]",
    "searchQuery" : "goo",
    "searchInteractionURIs" : [
    ]
  },
  {
    "platform" : "IPHONE_ARM64",
    "searchTime" : "2023-09-30T00:44:25.217Z[UTC]",
    "searchQuery" : "goo",
    "searchInteractionURIs" : [
    ]
  },
  {
    "platform" : "",
    "searchTime" : "2023-09-30T00:44:25.236Z[UTC]",
    "searchQuery" : "good",
    "searchInteractionURIs" : [
    ]
  },
  {
    "platform" : "",
    "searchTime" : "2023-09-30T00:44:25.304Z[UTC]",
    "searchQuery" : "good",
    "searchInteractionURIs" : [
    ]
  },
  {
    "platform" : "",
    "searchTime" : "2023-09-30T00:44:25.473Z[UTC]",
    "searchQuery" : "good ",
    "searchInteractionURIs" : [
    ]
  },
  {
    "platform" : "",
    "searchTime" : "2023-09-30T00:44:25.551Z[UTC]",
    "searchQuery" : "good ",
    "searchInteractionURIs" : [
    ]
  },
  {
    "platform" : "",
    "searchTime" : "2023-09-30T00:44:25.674Z[UTC]",
    "searchQuery" : "good m",
    "searchInteractionURIs" : [
    ]
  },
  {
    "platform" : "",
    "searchTime" : "2023-09-30T00:44:25.727Z[UTC]",
    "searchQuery" : "good m",
    "searchInteractionURIs" : [
    ]
  },
  {
    "platform" : "IPHONE_ARM64",
    "searchTime" : "2023-09-30T00:44:25.761Z[UTC]",
    "searchQuery" : "good ",
    "searchInteractionURIs" : [
    ]
  },
  {
    "platform" : "",
    "searchTime" : "2023-09-30T00:44:25.990Z[UTC]",
    "searchQuery" : "good my",
    "searchInteractionURIs" : [
    ]
  },
  {
    "platform" : "",
    "searchTime" : "2023-09-30T00:44:26.052Z[UTC]",
    "searchQuery" : "good my",
    "searchInteractionURIs" : [
    ]
  },
  {
    "platform" : "",
    "searchTime" : "2023-09-30T00:44:26.067Z[UTC]",
    "searchQuery" : "ear bu",
    "searchInteractionURIs" : [
    ]
  },
  {
    "platform" : "",
    "searchTime" : "2023-09-30T00:44:26.070Z[UTC]",
    "searchQuery" : "ear bis",
    "searchInteractionURIs" : [
    ]
  },
  {
    "platform" : "",
    "searchTime" : "2023-09-30T00:44:26.094Z[UTC]",
    "searchQuery" : "h3",
    "searchInteractionURIs" : [
    ]
  },
  {
    "platform" : "",
    "searchTime" : "2023-09-30T00:44:26.143Z[UTC]",
    "searchQuery" : "good myt",
    "searchInteractionURIs" : [
    ]
  },
  {
    "platform" : "",
    "searchTime" : "2023-09-30T00:44:26.189Z[UTC]",
    "searchQuery" : "good myt",
    "searchInteractionURIs" : [
    ]
  },
  {
    "platform" : "IPHONE",
    "searchTime" : "2023-09-30T00:44:26.434Z[UTC]",
    "searchQuery" : "good myt",
    "searchInteractionURIs" : [
      "spotify:show:2Odg2eA7CfPtBeFOz0Dr5D"
    ]
  },
  {
    "platform" : "IPHONE_ARM64",
    "searchTime" : "2023-09-30T03:25:22.902Z[UTC]",
    "searchQuery" : "fe",
    "searchInteractionURIs" : [
    ]
  },
  {
    "platform" : "IPHONE",
    "searchTime" : "2023-09-30T03:25:23.219Z[UTC]",
    "searchQuery" : "fein",
    "searchInteractionURIs" : [
      "spotify:track:42VsgItocQwOQC3XWZ8JNA"
    ]
  },
  {
    "platform" : "IPHONE_ARM64",
    "searchTime" : "2023-09-30T17:01:53.350Z[UTC]",
    "searchQuery" : "com",
    "searchInteractionURIs" : [
    ]
  },
  {
    "platform" : "IPHONE",
    "searchTime" : "2023-09-30T17:01:53.860Z[UTC]",
    "searchQuery" : "comed",
    "searchInteractionURIs" : [
      "spotify:album:4WnkQO4xD9ljQooB3VIxCV"
    ]
  },
  {
    "platform" : "IPHONE",
    "searchTime" : "2023-09-30T17:43:51.793Z[UTC]",
    "searchQuery" : "trav",
    "searchInteractionURIs" : [
      "spotify:album:18NOKLkZETa4sWwLMIm0UZ"
    ]
  },
  {
    "platform" : "IPHONE_ARM64",
    "searchTime" : "2023-09-30T18:52:25.215Z[UTC]",
    "searchQuery" : "ha",
    "searchInteractionURIs" : [
    ]
  },
  {
    "platform" : "IPHONE_ARM64",
    "searchTime" : "2023-09-30T18:52:26.098Z[UTC]",
    "searchQuery" : "half mo",
    "searchInteractionURIs" : [
    ]
  },
  {
    "platform" : "IPHONE",
    "searchTime" : "2023-09-30T18:52:26.339Z[UTC]",
    "searchQuery" : "half moo",
    "searchInteractionURIs" : [
      "spotify:artist:3ceQN2NVlLg1hgTzljDE4n"
    ]
  },
  {
    "platform" : "IPHONE_ARM64",
    "searchTime" : "2023-09-30T20:08:02.696Z[UTC]",
    "searchQuery" : "game ",
    "searchInteractionURIs" : [
    ]
  },
  {
    "platform" : "IPHONE",
    "searchTime" : "2023-09-30T20:08:03.420Z[UTC]",
    "searchQuery" : "game kf l",
    "searchInteractionURIs" : [
    ]
  },
  {
    "platform" : "IPHONE_ARM64",
    "searchTime" : "2023-10-01T02:44:49.762Z[UTC]",
    "searchQuery" : "sk",
    "searchInteractionURIs" : [
    ]
  },
  {
    "platform" : "IPHONE_ARM64",
    "searchTime" : "2023-10-01T02:44:50.036Z[UTC]",
    "searchQuery" : "skee",
    "searchInteractionURIs" : [
    ]
  },
  {
    "platform" : "IPHONE",
    "searchTime" : "2023-10-01T02:44:50.605Z[UTC]",
    "searchQuery" : "skeey",
    "searchInteractionURIs" : [
      "spotify:track:7icwQvajsokotDfM3tefW6"
    ]
  },
  {
    "platform" : "IPHONE",
    "searchTime" : "2023-10-01T02:47:58.615Z[UTC]",
    "searchQuery" : "speed ",
    "searchInteractionURIs" : [
      "spotify:track:7GRv55NwkjxU2ysJLwzC9c"
    ]
  },
  {
    "platform" : "IPHONE",
    "searchTime" : "2023-10-01T02:48:05.934Z[UTC]",
    "searchQuery" : "claws",
    "searchInteractionURIs" : [
      "spotify:track:7Dexi5Z2IowCkHrnzlWysc"
    ]
  },
  {
    "platform" : "IPHONE_ARM64",
    "searchTime" : "2023-10-01T02:48:19.285Z[UTC]",
    "searchQuery" : "c",
    "searchInteractionURIs" : [
    ]
  },
  {
    "platform" : "IPHONE_ARM64",
    "searchTime" : "2023-10-01T02:48:22.196Z[UTC]",
    "searchQuery" : "carl",
    "searchInteractionURIs" : [
    ]
  },
  {
    "platform" : "IPHONE",
    "searchTime" : "2023-10-01T02:48:22.942Z[UTC]",
    "searchQuery" : "carli",
    "searchInteractionURIs" : [
      "spotify:artist:25uiPmTg16RbhZWAqwLBy5"
    ]
  },
  {
    "platform" : "IPHONE",
    "searchTime" : "2023-10-02T17:36:38.855Z[UTC]",
    "searchQuery" : "kid a",
    "searchInteractionURIs" : [
      "spotify:album:6GjwtEZcfenmOf6l18N7T7"
    ]
  },
  {
    "platform" : "IPHONE",
    "searchTime" : "2023-10-03T19:52:04.368Z[UTC]",
    "searchQuery" : "rep",
    "searchInteractionURIs" : [
      "spotify:track:57Xjny5yNzAcsxnusKmAfA"
    ]
  },
  {
    "platform" : "",
    "searchTime" : "2023-10-04T00:57:11.859Z[UTC]",
    "searchQuery" : "d",
    "searchInteractionURIs" : [
    ]
  },
  {
    "platform" : "",
    "searchTime" : "2023-10-04T00:57:11.928Z[UTC]",
    "searchQuery" : "d",
    "searchInteractionURIs" : [
    ]
  },
  {
    "platform" : "",
    "searchTime" : "2023-10-04T00:57:11.994Z[UTC]",
    "searchQuery" : "dr",
    "searchInteractionURIs" : [
    ]
  },
  {
    "platform" : "",
    "searchTime" : "2023-10-04T00:57:12.045Z[UTC]",
    "searchQuery" : "dr",
    "searchInteractionURIs" : [
    ]
  },
  {
    "platform" : "",
    "searchTime" : "2023-10-04T00:57:12.230Z[UTC]",
    "searchQuery" : "dra",
    "searchInteractionURIs" : [
    ]
  },
  {
    "platform" : "",
    "searchTime" : "2023-10-04T00:57:12.287Z[UTC]",
    "searchQuery" : "dra",
    "searchInteractionURIs" : [
    ]
  },
  {
    "platform" : "",
    "searchTime" : "2023-10-04T00:57:12.569Z[UTC]",
    "searchQuery" : "drak",
    "searchInteractionURIs" : [
    ]
  },
  {
    "platform" : "",
    "searchTime" : "2023-10-04T00:57:12.633Z[UTC]",
    "searchQuery" : "drak",
    "searchInteractionURIs" : [
    ]
  },
  {
    "platform" : "IPHONE",
    "searchTime" : "2023-10-04T00:57:12.899Z[UTC]",
    "searchQuery" : "drak",
    "searchInteractionURIs" : [
      "spotify:artist:3TVXtAsR1Inumwj472S9r4"
    ]
  },
  {
    "platform" : "IPHONE_ARM64",
    "searchTime" : "2023-10-05T21:47:34.015Z[UTC]",
    "searchQuery" : "g",
    "searchInteractionURIs" : [
    ]
  },
  {
    "platform" : "IPHONE",
    "searchTime" : "2023-10-05T21:47:35.053Z[UTC]",
    "searchQuery" : "groupi",
    "searchInteractionURIs" : [
      "spotify:track:03hqMhmCZiNKMSPmVabPLP"
    ]
  },
  {
    "platform" : "IPHONE",
    "searchTime" : "2023-10-06T04:15:17.853Z[UTC]",
    "searchQuery" : "kanye",
    "searchInteractionURIs" : [
      "spotify:artist:5K4W6rqBFWDnAN6FQUkS6x"
    ]
  },
  {
    "platform" : "IPHONE_ARM64",
    "searchTime" : "2023-10-06T17:25:46.811Z[UTC]",
    "searchQuery" : "j ",
    "searchInteractionURIs" : [
    ]
  },
  {
    "platform" : "IPHONE",
    "searchTime" : "2023-10-06T17:25:47.546Z[UTC]",
    "searchQuery" : "j col",
    "searchInteractionURIs" : [
      "spotify:artist:6l3HvQ5sa6mXTsMTB19rO5"
    ]
  },
  {
    "platform" : "IPHONE_ARM64",
    "searchTime" : "2023-10-07T16:05:35.807Z[UTC]",
    "searchQuery" : "a",
    "searchInteractionURIs" : [
    ]
  },
  {
    "platform" : "IPHONE_ARM64",
    "searchTime" : "2023-10-07T16:05:36.035Z[UTC]",
    "searchQuery" : "arc",
    "searchInteractionURIs" : [
    ]
  },
  {
    "platform" : "IPHONE",
    "searchTime" : "2023-10-07T16:05:36.630Z[UTC]",
    "searchQuery" : "arctic",
    "searchInteractionURIs" : [
      "spotify:artist:7Ln80lUS6He07XvHI8qqHH"
    ]
  },
  {
    "platform" : "IPHONE",
    "searchTime" : "2023-10-08T16:46:13.417Z[UTC]",
    "searchQuery" : "dawn",
    "searchInteractionURIs" : [
      "spotify:album:2nLOHgzXzwFEpl62zAgCEC"
    ]
  },
  {
    "platform" : "IPHONE",
    "searchTime" : "2023-10-08T17:47:33.675Z[UTC]",
    "searchQuery" : "mm food",
    "searchInteractionURIs" : [
      "spotify:album:1UcS2nqUhxrZjrBZ3tHk2N"
    ]
  },
  {
    "platform" : "IPHONE_ARM64",
    "searchTime" : "2023-10-10T04:04:14.960Z[UTC]",
    "searchQuery" : "in rai",
    "searchInteractionURIs" : [
    ]
  },
  {
    "platform" : "IPHONE",
    "searchTime" : "2023-10-10T04:04:15.181Z[UTC]",
    "searchQuery" : "in rain",
    "searchInteractionURIs" : [
      "spotify:album:5vkqYmiPBYLaalcmjujWxK",
      "spotify:album:6zTAW5oRuOmxJuUHhcQope",
      "spotify:album:5vkqYmiPBYLaalcmjujWxK"
    ]
  },
  {
    "platform" : "IPHONE_ARM64",
    "searchTime" : "2023-10-11T01:51:41.753Z[UTC]",
    "searchQuery" : "m",
    "searchInteractionURIs" : [
    ]
  },
  {
    "platform" : "IPHONE_ARM64",
    "searchTime" : "2023-10-11T01:51:42.530Z[UTC]",
    "searchQuery" : "madde",
    "searchInteractionURIs" : [
    ]
  },
  {
    "platform" : "IPHONE",
    "searchTime" : "2023-10-11T01:51:42.887Z[UTC]",
    "searchQuery" : "madden ",
    "searchInteractionURIs" : [
      "spotify:playlist:249pO85bmu92slnggHUEXi"
    ]
  },
  {
    "platform" : "IPHONE_ARM64",
    "searchTime" : "2023-10-11T14:58:58.142Z[UTC]",
    "searchQuery" : "circ",
    "searchInteractionURIs" : [
    ]
  },
  {
    "platform" : "IPHONE",
    "searchTime" : "2023-10-11T14:59:00.759Z[UTC]",
    "searchQuery" : "circus maxi",
    "searchInteractionURIs" : [
      "spotify:search:circus+maximus+setlist"
    ]
  },
  {
    "platform" : "IPHONE",
    "searchTime" : "2023-10-11T14:59:02.190Z[UTC]",
    "searchQuery" : "circus maximus setlist",
    "searchInteractionURIs" : [
      "spotify:playlist:21yXfdtWCAHB316aGoUg7s"
    ]
  },
  {
    "platform" : "IPHONE",
    "searchTime" : "2023-10-11T16:35:22.439Z[UTC]",
    "searchQuery" : "jpe",
    "searchInteractionURIs" : [
      "spotify:artist:6yJ6QQ3Y5l0s0tn7b0arrO"
    ]
  },
  {
    "platform" : "IPHONE",
    "searchTime" : "2023-10-15T23:53:46.956Z[UTC]",
    "searchQuery" : "drake",
    "searchInteractionURIs" : [
      "spotify:artist:3TVXtAsR1Inumwj472S9r4"
    ]
  },
  {
    "platform" : "IPHONE",
    "searchTime" : "2023-10-15T23:53:57.273Z[UTC]",
    "searchQuery" : "adojis",
    "searchInteractionURIs" : [
    ]
  },
  {
    "platform" : "IPHONE",
    "searchTime" : "2023-10-16T14:52:22.123Z[UTC]",
    "searchQuery" : "dopam",
    "searchInteractionURIs" : [
      "spotify:album:17l7MIu0Jh0tdgK7or9ovw"
    ]
  },
  {
    "platform" : "IPHONE_ARM64",
    "searchTime" : "2023-10-17T02:29:58.726Z[UTC]",
    "searchQuery" : "as",
    "searchInteractionURIs" : [
    ]
  },
  {
    "platform" : "IPHONE",
    "searchTime" : "2023-10-17T02:29:59.934Z[UTC]",
    "searchQuery" : "austin",
    "searchInteractionURIs" : [
      "spotify:album:6r1lh7fHMB499vGKtIyJLy"
    ]
  },
  {
    "platform" : "IPHONE",
    "searchTime" : "2023-10-17T22:27:28.568Z[UTC]",
    "searchQuery" : "ken car",
    "searchInteractionURIs" : [
      "spotify:album:0HS8aknH0JQdMIiBVhyOCW"
    ]
  },
  {
    "platform" : "IPHONE_ARM64",
    "searchTime" : "2023-10-19T14:33:55.026Z[UTC]",
    "searchQuery" : "ast",
    "searchInteractionURIs" : [
    ]
  },
  {
    "platform" : "IPHONE",
    "searchTime" : "2023-10-19T14:33:55.537Z[UTC]",
    "searchQuery" : "astro",
    "searchInteractionURIs" : [
      "spotify:album:41GuZcammIkupMPKH2OJ6I"
    ]
  },
  {
    "platform" : "IPHONE",
    "searchTime" : "2023-10-19T22:52:16.626Z[UTC]",
    "searchQuery" : "idgaf",
    "searchInteractionURIs" : [
      "spotify:track:2YSzYUF3jWqb9YP9VXmpjE"
    ]
  },
  {
    "platform" : "IPHONE_ARM64",
    "searchTime" : "2023-10-20T04:16:33.339Z[UTC]",
    "searchQuery" : "drugs y",
    "searchInteractionURIs" : [
    ]
  },
  {
    "platform" : "IPHONE",
    "searchTime" : "2023-10-20T04:16:33.812Z[UTC]",
    "searchQuery" : "drugs you ",
    "searchInteractionURIs" : [
      "spotify:playlist:07kQQavcVyrMeH8linvIiu",
      "spotify:album:42WVQWuf1teDysXiOupIZt"
    ]
  },
  {
    "platform" : "IPHONE_ARM64",
    "searchTime" : "2023-10-20T17:25:30.821Z[UTC]",
    "searchQuery" : "b",
    "searchInteractionURIs" : [
    ]
  },
  {
    "platform" : "IPHONE_ARM64",
    "searchTime" : "2023-10-20T17:25:31.102Z[UTC]",
    "searchQuery" : "burn",
    "searchInteractionURIs" : [
    ]
  },
  {
    "platform" : "IPHONE_ARM64",
    "searchTime" : "2023-10-20T17:25:31.600Z[UTC]",
    "searchQuery" : "burn a",
    "searchInteractionURIs" : [
    ]
  },
  {
    "platform" : "IPHONE",
    "searchTime" : "2023-10-20T17:25:32.257Z[UTC]",
    "searchQuery" : "burn after",
    "searchInteractionURIs" : [
      "spotify:show:0CXoIrHa7Dcdv4szxNvUqr"
    ]
  },
  {
    "platform" : "IPHONE",
    "searchTime" : "2023-10-20T17:43:20.700Z[UTC]",
    "searchQuery" : "borns",
    "searchInteractionURIs" : [
      "spotify:artist:1KP6TWI40m7p3QBTU6u2xo"
    ]
  },
  {
    "platform" : "IPHONE_ARM64",
    "searchTime" : "2023-10-20T17:43:21.709Z[UTC]",
    "searchQuery" : "Børns",
    "searchInteractionURIs" : [
    ]
  },
  {
    "platform" : "IPHONE_ARM64",
    "searchTime" : "2023-10-20T17:57:44.680Z[UTC]",
    "searchQuery" : "th",
    "searchInteractionURIs" : [
    ]
  },
  {
    "platform" : "IPHONE_ARM64",
    "searchTime" : "2023-10-20T17:57:45.119Z[UTC]",
    "searchQuery" : "the ",
    "searchInteractionURIs" : [
    ]
  },
  {
    "platform" : "IPHONE",
    "searchTime" : "2023-10-20T17:57:45.455Z[UTC]",
    "searchQuery" : "the b",
    "searchInteractionURIs" : [
      "spotify:album:35UJLpClj5EDrhpNIi4DFg"
    ]
  },
  {
    "platform" : "IPHONE",
    "searchTime" : "2023-10-21T13:59:35.992Z[UTC]",
    "searchQuery" : "juli",
    "searchInteractionURIs" : [
      "spotify:artist:1rAv1GhTQ2rmG94p9lU3rB"
    ]
  },
  {
    "platform" : "IPHONE",
    "searchTime" : "2023-10-21T15:56:35.480Z[UTC]",
    "searchQuery" : "rodeo",
    "searchInteractionURIs" : [
      "spotify:album:4PWBTB6NYSKQwfo79I3prg"
    ]
  },
  {
    "platform" : "IPHONE_ARM64",
    "searchTime" : "2023-10-22T16:39:04.435Z[UTC]",
    "searchQuery" : "wh",
    "searchInteractionURIs" : [
    ]
  },
  {
    "platform" : "IPHONE",
    "searchTime" : "2023-10-22T16:39:05.468Z[UTC]",
    "searchQuery" : "why are",
    "searchInteractionURIs" : [
      "spotify:album:2xkZV2Hl1Omi8rk2D7t5lN"
    ]
  }
]